Workbook
Name Days: #REF!
Name Days: 'FRI-Dataset'!$D$2
Name Days: #REF!
Name ProjectYears: #REF!
Name ProjectYears: #REF!
Name ProjectYears: #REF!
Name SectorCodes: #REF!
Name SectorCodes: #REF!
Name SectorCodes: #REF!
Name SectorCodes: #REF!
Name SectorNames: #REF!
Name SectorNames: #REF!
Name SectorNames: #REF!
Name SectorNames: #REF!

Sheet Cover
B2: Toward an Integrated Assessment of Financial Resilience and Governance in Tunisian Non-Listed SMEs
A7: WORKBOOK NAVIGATION
A9: DATA & METHODOLOGY FOUNDATIONS | K9: PORTFOLIO MAPPING
A10: FRI-Dataset | K10: Cluster Firms
A11: Formula Dictionary | K11: Cluster Summary
A12: Sector Grouping | K12: Silhouette
A13: PCA Diagnostics | K13: Benchmarking
A14: STATISTICAL EVIDENCE | K14: DECISION SUPPORT APPLICATION
A15: FRI Results | K15: Decision Table
A16: FRI by Firm | K16: Sensitivity Analysis
A17: Descriptives | K17: Case Study
A18: Spearman | K18: CORRELATION ANALYSIS & VISUALS
A19: Bootstrap | K19: Pillar Correlations
A20: Wilcoxon | K20: FRI Visualizations
A21: Governance Score | K21: Decision Framework – Charts
A22: G_score vs FRI
A23: Synthesis

Sheet FRI-Dataset
B1: IRF Pillars Calculator
B2: Days | D2: 365
B4: Identifiers | E4: Raw Inputs / Controls | U4: Derived Input | V4: Liquidity | Y4: Cash Generation | AB4: Capital Structure | AE4: Debt Sustainability
B5: Firm_ID | C5: Sector | D5: Year | E5: Revenue | F5: Current Assets | G5: Current Liabilities | H5: Cash & Cash Eq. | I5: Accounts Receivables | J5: Total Assets | K5: ST Debt | L5: LT Debt | M5: Total Equity | N5: Retained Earnings | O5: EBIT | P5: Interest Expense | Q5: Net Income | R5: Depreciation & Amort. | S5: Cash flow from oprations | T5: EBITDA | U5: Total Financial Debt | V5: Current Ratio | W5: Working Capital / Total Assets | X5: Receivables Days | Y5: EBITDA / Total Assets | Z5: CFO / Revenue | AA5: Asset Turnover | AB5: Equity Ratio | AC5: Financial Debt / TA | AD5: Retained Earnings / TA | AE5: Interest Coverage Ratio (ICR) | AF5: CFO / Interest Coverage | AG5: CFO / Financial Debt
B6: F01 | C6: =_xlfn.XLOOKUP(B6,Sector_Grouping!$A$4:$A$18,Sector_Grouping!$C$4:$C$18,"") -> Services and Commerce | D6: 2020 | E6: 20211488 | F6: 11228835 | G6: 13091101 | H6: 89079.112 | I6: 2743202.8 | J6: 24794637 | K6: 1763525.8 | L6: 6692537.4 | M6: 4458554.4 | N6: 3812210.1 | O6: -409817.08 | P6: 429897.77 | Q6: -537954.7 | R6: 1525847.5 | S6: -1205642.8 | T6: =O6+R6 -> 1116030.4 | U6: =K6+L6 -> 8456063.2 | V6: =IF(G6=0,"",F6/G6) -> 0.85774565 | W6: =IF(J6=0,"",(F6-G6)/J6) -> -0.075107612 | X6: =IF(E6=0,"",(I6/E6)*Days) -> 49.539599 | Y6: =IF(J6=0,"",T6/J6) -> 0.04501096 | Z6: =IF(E6=0,"",S6/E6) -> -0.059651359 | AA6: =IF(J6=0,"",E6/J6) -> 0.81515564 | AB6: =IF(U6=0,"",M6/J6) -> 0.1798193 | AC6: =IF(J6=0,"",U6/J6) -> 0.34104404 | AD6: =IF(J6=0,"",N6/J6) -> 0.1537514 | AE6: =IF(P6=0,"",O6/P6) -> -0.95328961 | AF6: =IF(P6=0,"N/A",S6/P6) -> -2.8044871 | AG6: =IF(U6=0,"",(S6/U6)) -> -0.14257731
B7: F01 | C7: =_xlfn.XLOOKUP(B7,Sector_Grouping!$A$4:$A$18,Sector_Grouping!$C$4:$C$18,"") -> Services and Commerce | D7: 2021 | E7: 23721959 | F7: 13720759 | G7: 14137495 | H7: 380068.85 | I7: 3501099.3 | J7: 25643521 | K7: 1533193.7 | L7: 7407135.8 | M7: 3546445.4 | N7: 3274255.4 | O7: -194852.1 | P7: 841464.76 | Q7: -912108.97 | R7: 1616805.8 | S7: -219511.6 | T7: =O7+R7 -> 1421953.7 | U7: =K7+L7 -> 8940329.5 | V7: =IF(G7=0,"",F7/G7) -> 0.97052266 | W7: =IF(J7=0,"",(F7-G7)/J7) -> -0.01625111 | X7: =IF(E7=0,"",(I7/E7)*Days) -> 53.869972 | Y7: =IF(J7=0,"",T7/J7) -> 0.0554508 | Z7: =IF(E7=0,"",S7/E7) -> -0.009253519 | AA7: =IF(J7=0,"",E7/J7) -> 0.92506636 | AB7: =IF(U7=0,"",M7/J7) -> 0.13829791 | AC7: =IF(J7=0,"",U7/J7) -> 0.34863892 | AD7: =IF(J7=0,"",N7/J7) -> 0.12768353 | AE7: =IF(P7=0,"",O7/P7) -> -0.23156299 | AF7: =IF(P7=0,"N/A",S7/P7) -> -0.26086844 | AG7: =IF(U7=0,"",(S7/U7)) -> -0.024552965
B8: F01 | C8: =_xlfn.XLOOKUP(B8,Sector_Grouping!$A$4:$A$18,Sector_Grouping!$C$4:$C$18,"") -> Services and Commerce | D8: 2022 | E8: 35432832 | F8: 15461713 | G8: 15738947 | H8: 500009.47 | I8: 4157035.2 | J8: 26589496 | K8: 2480676.6 | L8: 5719600.9 | M8: 3978503.1 | N8: 2362146.4 | O8: 1055584.1 | P8: 857643.64 | Q8: 432057.73 | R8: =2207265.985 -> 2207266 | S8: 1672279.6 | T8: =O8+R8 -> 3262850.1 | U8: =K8+L8 -> 8200277.5 | V8: =IF(G8=0,"",F8/G8) -> 0.98238548 | W8: =IF(J8=0,"",(F8-G8)/J8) -> -0.010426446 | X8: =IF(E8=0,"",(I8/E8)*Days) -> 42.82237 | Y8: =IF(J8=0,"",T8/J8) -> 0.12271199 | Z8: =IF(E8=0,"",S8/E8) -> 0.047195765 | AA8: =IF(J8=0,"",E8/J8) -> 1.3325876 | AB8: =IF(U8=0,"",M8/J8) -> 0.14962687 | AC8: =IF(J8=0,"",U8/J8) -> 0.30840289 | AD8: =IF(J8=0,"",N8/J8) -> 0.088837576 | AE8: =IF(P8=0,"",O8/P8) -> 1.2307957 | AF8: =IF(P8=0,"N/A",S8/P8) -> 1.9498537 | AG8: =IF(U8=0,"",(S8/U8)) -> 0.20392964
B9: F01 | C9: =_xlfn.XLOOKUP(B9,Sector_Grouping!$A$4:$A$18,Sector_Grouping!$C$4:$C$18,"") -> Services and Commerce | D9: 2023 | E9: 42035572 | F9: 19340584 | G9: 18951398 | H9: 478135.48 | I9: 5895796.7 | J9: 37225084 | K9: 2754138 | L9: 5099463.1 | M9: 11311746 | N9: 3560058.6 | O9: 1985418.1 | P9: 814494.57 | Q9: 1577369.8 | R9: 1403777.4 | S9: 3603121.9 | T9: =O9+R9 -> 3389195.5 | U9: =K9+L9 -> 7853601.1 | V9: =IF(G9=0,"",F9/G9) -> 1.020536 | W9: =IF(J9=0,"",(F9-G9)/J9) -> 0.010454941 | X9: =IF(E9=0,"",(I9/E9)*Days) -> 51.193922 | Y9: =IF(J9=0,"",T9/J9) -> 0.091046016 | Z9: =IF(E9=0,"",S9/E9) -> 0.08571602 | AA9: =IF(J9=0,"",E9/J9) -> 1.1292271 | AB9: =IF(U9=0,"",M9/J9) -> 0.3038743 | AC9: =IF(J9=0,"",U9/J9) -> 0.21097605 | AD9: =IF(J9=0,"",N9/J9) -> 0.095636015 | AE9: =IF(P9=0,"",O9/P9) -> 2.4376075 | AF9: =IF(P9=0,"N/A",S9/P9) -> 4.4237519 | AG9: =IF(U9=0,"",(S9/U9)) -> 0.45878596
B10: F01 | C10: =_xlfn.XLOOKUP(B10,Sector_Grouping!$A$4:$A$18,Sector_Grouping!$C$4:$C$18,"") -> Services and Commerce | D10: 2024 | E10: 44599721 | F10: 18286877 | G10: 18971261 | H10: 150043.35 | I10: 7189025.2 | J10: 36139692 | K10: 2313320.4 | L10: 3586120.5 | M10: 11219835 | N10: 3637428.4 | O10: 2547485.7 | P10: 779039.83 | Q10: 1408088.7 | R10: 1353618.6 | S10: 5094359.3 | T10: =O10+R10 -> 3901104.4 | U10: =K10+L10 -> 5899440.9 | V10: =IF(G10=0,"",F10/G10) -> 0.96392524 | W10: =IF(J10=0,"",(F10-G10)/J10) -> -0.018937174 | X10: =IF(E10=0,"",(I10/E10)*Days) -> 58.834318 | Y10: =IF(J10=0,"",T10/J10) -> 0.10794515 | Z10: =IF(E10=0,"",S10/E10) -> 0.11422402 | AA10: =IF(J10=0,"",E10/J10) -> 1.2340925 | AB10: =IF(U10=0,"",M10/J10) -> 0.3104574 | AC10: =IF(J10=0,"",U10/J10) -> 0.16323993 | AD10: =IF(J10=0,"",N10/J10) -> 0.10064913 | AE10: =IF(P10=0,"",O10/P10) -> 3.2700327 | AF10: =IF(P10=0,"N/A",S10/P10) -> 6.5392796 | AG10: =IF(U10=0,"",(S10/U10)) -> 0.86353255
B11: F02 | C11: =_xlfn.XLOOKUP(B11,Sector_Grouping!$A$4:$A$18,Sector_Grouping!$C$4:$C$18,"") -> Agri-food Industry | D11: 2020 | E11: 1512928 | F11: 1570443 | G11: 2262342 | H11: 3935 | I11: 572727 | J11: 4246985 | K11: 923434 | L11: 1702146 | M11: 282497 | N11: 331269 | O11: -446151 | P11: 136724 | Q11: -548772 | R11: 208539 | S11: -312346 | T11: =O11+R11 -> -237612 | U11: =K11+L11 -> 2625580 | V11: =IF(G11=0,"",F11/G11) -> 0.69416693 | W11: =IF(J11=0,"",(F11-G11)/J11) -> -0.16291534 | X11: =IF(E11=0,"",(I11/E11)*Days) -> 138.17271 | Y11: =IF(J11=0,"",T11/J11) -> -0.055948396 | Z11: =IF(E11=0,"",S11/E11) -> -0.20645133 | AA11: =IF(J11=0,"",E11/J11) -> 0.35623578 | AB11: =IF(U11=0,"",M11/J11) -> 0.06651707 | AC11: =IF(J11=0,"",U11/J11) -> 0.6182221 | AD11: =IF(J11=0,"",N11/J11) -> 0.078000982 | AE11: =IF(P11=0,"",O11/P11) -> -3.2631506 | AF11: =IF(P11=0,"N/A",S11/P11) -> -2.2845002 | AG11: =IF(U11=0,"",(S11/U11)) -> -0.11896267
B12: F02 | C12: =_xlfn.XLOOKUP(B12,Sector_Grouping!$A$4:$A$18,Sector_Grouping!$C$4:$C$18,"") -> Agri-food Industry | D12: 2021 | E12: 2810637 | F12: 1536296 | G12: 2554314 | H12: 10045 | I12: 110607 | J12: 3998376 | K12: 801064 | L12: 1350130 | M12: 93932 | N12: -217503 | O12: -133466 | P12: 236369 | Q12: -384107 | R12: 287785 | S12: 528332 | T12: =O12+R12 -> 154319 | U12: =K12+L12 -> 2151194 | V12: =IF(G12=0,"",F12/G12) -> 0.60145151 | W12: =IF(J12=0,"",(F12-G12)/J12) -> -0.25460787 | X12: =IF(E12=0,"",(I12/E12)*Days) -> 14.363845 | Y12: =IF(J12=0,"",T12/J12) -> 0.03859542 | Z12: =IF(E12=0,"",S12/E12) -> 0.18797589 | AA12: =IF(J12=0,"",E12/J12) -> 0.70294465 | AB12: =IF(U12=0,"",M12/J12) -> 0.023492538 | AC12: =IF(J12=0,"",U12/J12) -> 0.53801693 | AD12: =IF(J12=0,"",N12/J12) -> -0.054397836 | AE12: =IF(P12=0,"",O12/P12) -> -0.56465103 | AF12: =IF(P12=0,"N/A",S12/P12) -> 2.2352 | AG12: =IF(U12=0,"",(S12/U12)) -> 0.24559942
B13: F02 | C13: =_xlfn.XLOOKUP(B13,Sector_Grouping!$A$4:$A$18,Sector_Grouping!$C$4:$C$18,"") -> Agri-food Industry | D13: 2022 | E13: 3249128 | F13: 1820736 | G13: 2166536 | H13: 76656 | I13: 1120515 | J13: 3987351 | K13: 415700 | L13: 1044188 | M13: 776267 | N13: -601609 | O13: -1058060 | P13: 204287 | Q13: -1234257 | R13: 296792 | S13: -495792 | T13: =O13+R13 -> -761268 | U13: =K13+L13 -> 1459888 | V13: =IF(G13=0,"",F13/G13) -> 0.84039037 | W13: =IF(J13=0,"",(F13-G13)/J13) -> -0.086724244 | X13: =IF(E13=0,"",(I13/E13)*Days) -> 125.87623 | Y13: =IF(J13=0,"",T13/J13) -> -0.19092074 | Z13: =IF(E13=0,"",S13/E13) -> -0.15259233 | AA13: =IF(J13=0,"",E13/J13) -> 0.81485879 | AB13: =IF(U13=0,"",M13/J13) -> 0.19468238 | AC13: =IF(J13=0,"",U13/J13) -> 0.36612979 | AD13: =IF(J13=0,"",N13/J13) -> -0.15087937 | AE13: =IF(P13=0,"",O13/P13) -> -5.1792821 | AF13: =IF(P13=0,"N/A",S13/P13) -> -2.4269386 | AG13: =IF(U13=0,"",(S13/U13)) -> -0.33960961
B14: F02 | C14: =_xlfn.XLOOKUP(B14,Sector_Grouping!$A$4:$A$18,Sector_Grouping!$C$4:$C$18,"") -> Agri-food Industry | D14: 2023 | E14: 3690444 | F14: 2045339 | G14: 2234983 | H14: 12711 | I14: 1183251 | J14: 3761604 | K14: 1046429 | L14: 635072 | M14: 891549 | N14: -1835866 | O14: 68244 | P14: 199249 | Q14: 147971 | R14: 307388 | S14: -125302 | T14: =O14+R14 -> 375632 | U14: =K14+L14 -> 1681501 | V14: =IF(G14=0,"",F14/G14) -> 0.91514745 | W14: =IF(J14=0,"",(F14-G14)/J14) -> -0.050415727 | X14: =IF(E14=0,"",(I14/E14)*Days) -> 117.02836 | Y14: =IF(J14=0,"",T14/J14) -> 0.099859528 | Z14: =IF(E14=0,"",S14/E14) -> -0.033953096 | AA14: =IF(J14=0,"",E14/J14) -> 0.98108254 | AB14: =IF(U14=0,"",M14/J14) -> 0.23701299 | AC14: =IF(J14=0,"",U14/J14) -> 0.44701702 | AD14: =IF(J14=0,"",N14/J14) -> -0.48805403 | AE14: =IF(P14=0,"",O14/P14) -> 0.34250611 | AF14: =IF(P14=0,"N/A",S14/P14) -> -0.62887141 | AG14: =IF(U14=0,"",(S14/U14)) -> -0.074517946
B15: F02 | C15: =_xlfn.XLOOKUP(B15,Sector_Grouping!$A$4:$A$18,Sector_Grouping!$C$4:$C$18,"") -> Agri-food Industry | D15: 2024 | E15: 5346533 | F15: 2458925 | G15: 2609560 | H15: 8722 | I15: 1774422 | J15: 4014786 | K15: 896697 | L15: 382582 | M15: 1022645 | N15: -1687895 | O15: 271581 | P15: 168321 | Q15: 164146 | R15: 277248 | S15: 556954 | T15: =O15+R15 -> 548829 | U15: =K15+L15 -> 1279279 | V15: =IF(G15=0,"",F15/G15) -> 0.94227571 | W15: =IF(J15=0,"",(F15-G15)/J15) -> -0.037520057 | X15: =IF(E15=0,"",(I15/E15)*Days) -> 121.1372 | Y15: =IF(J15=0,"",T15/J15) -> 0.13670193 | Z15: =IF(E15=0,"",S15/E15) -> 0.10417106 | AA15: =IF(J15=0,"",E15/J15) -> 1.3317106 | AB15: =IF(U15=0,"",M15/J15) -> 0.25471968 | AC15: =IF(J15=0,"",U15/J15) -> 0.31864189 | AD15: =IF(J15=0,"",N15/J15) -> -0.42041967 | AE15: =IF(P15=0,"",O15/P15) -> 1.6134707 | AF15: =IF(P15=0,"N/A",S15/P15) -> 3.3088801 | AG15: =IF(U15=0,"",(S15/U15)) -> 0.43536555
B16: F03 | C16: =_xlfn.XLOOKUP(B16,Sector_Grouping!$A$4:$A$18,Sector_Grouping!$C$4:$C$18,"") -> Manufacturing Industry | D16: 2019 | E16: 6338113 | F16: 3392695 | G16: 6873941 | H16: 672231 | I16: =519274-130000 -> 389274 | J16: 7633761 | K16: 4737871 | L16: 2505819 | M16: -1745999 | N16: -3385519 | O16: -2114355 | P16: 531863 | Q16: -2630480 | R16: 767019 | S16: -1342190 | T16: =O16+R16 -> -1347336 | U16: =K16+L16 -> 7243690 | V16: =IF(G16=0,"",F16/G16) -> 0.49355894 | W16: =IF(J16=0,"",(F16-G16)/J16) -> -0.45603288 | X16: =IF(E16=0,"",(I16/E16)*Days) -> 22.417557 | Y16: =IF(J16=0,"",T16/J16) -> -0.17649701 | Z16: =IF(E16=0,"",S16/E16) -> -0.21176492 | AA16: =IF(J16=0,"",E16/J16) -> 0.83027396 | AB16: =IF(U16=0,"",M16/J16) -> -0.22872068 | AC16: =IF(J16=0,"",U16/J16) -> 0.94890186 | AD16: =IF(J16=0,"",N16/J16) -> -0.44349293 | AE16: =IF(P16=0,"",O16/P16) -> -3.9753752 | AF16: =IF(P16=0,"N/A",S16/P16) -> -2.5235634 | AG16: =IF(U16=0,"",(S16/U16)) -> -0.18529092
B17: F03 | C17: =_xlfn.XLOOKUP(B17,Sector_Grouping!$A$4:$A$18,Sector_Grouping!$C$4:$C$18,"") -> Manufacturing Industry | D17: 2020 | E17: 7138021 | F17: 2555873 | G17: 6995276 | H17: 268571 | I17: =387139-130000 -> 257139 | J17: 6046469 | K17: 4891333 | L17: 1722487 | M17: -2671295 | N17: -6015999 | O17: -1073237 | P17: 602059 | Q17: -1675296 | R17: 330873 | S17: -253551 | T17: =O17+R17 -> -742364 | U17: =K17+L17 -> 6613820 | V17: =IF(G17=0,"",F17/G17) -> 0.36537129 | W17: =IF(J17=0,"",(F17-G17)/J17) -> -0.73421413 | X17: =IF(E17=0,"",(I17/E17)*Days) -> 13.148705 | Y17: =IF(J17=0,"",T17/J17) -> -0.12277645 | Z17: =IF(E17=0,"",S17/E17) -> -0.03552119 | AA17: =IF(J17=0,"",E17/J17) -> 1.1805272 | AB17: =IF(U17=0,"",M17/J17) -> -0.44179421 | AC17: =IF(J17=0,"",U17/J17) -> 1.0938318 | AD17: =IF(J17=0,"",N17/J17) -> -0.9949607 | AE17: =IF(P17=0,"",O17/P17) -> -1.782611 | AF17: =IF(P17=0,"N/A",S17/P17) -> -0.42113979 | AG17: =IF(U17=0,"",(S17/U17)) -> -0.038336544
B18: F03 | C18: =_xlfn.XLOOKUP(B18,Sector_Grouping!$A$4:$A$18,Sector_Grouping!$C$4:$C$18,"") -> Manufacturing Industry | D18: 2021 | E18: 6749699 | F18: 8270343 | G18: 12348543 | H18: 336198 | I18: 380455 | J18: 10917014 | K18: 7430949 | L18: 1451518 | M18: -2947819 | N18: -9886679 | O18: -2495667 | P18: 779197 | Q18: -3081140 | R18: 1307874 | S18: -4888746 | T18: =O18+R18 -> -1187793 | U18: =K18+L18 -> 8882467 | V18: =IF(G18=0,"",F18/G18) -> 0.66974241 | W18: =IF(J18=0,"",(F18-G18)/J18) -> -0.37356369 | X18: =IF(E18=0,"",(I18/E18)*Days) -> 20.573669 | Y18: =IF(J18=0,"",T18/J18) -> -0.108802 | Z18: =IF(E18=0,"",S18/E18) -> -0.72429096 | AA18: =IF(J18=0,"",E18/J18) -> 0.61827337 | AB18: =IF(U18=0,"",M18/J18) -> -0.27002063 | AC18: =IF(J18=0,"",U18/J18) -> 0.81363521 | AD18: =IF(J18=0,"",N18/J18) -> -0.90562117 | AE18: =IF(P18=0,"",O18/P18) -> -3.2028704 | AF18: =IF(P18=0,"N/A",S18/P18) -> -6.2740822 | AG18: =IF(U18=0,"",(S18/U18)) -> -0.55038156
B19: F03 | C19: =_xlfn.XLOOKUP(B19,Sector_Grouping!$A$4:$A$18,Sector_Grouping!$C$4:$C$18,"") -> Manufacturing Industry | D19: 2022 | E19: 8951813 | F19: 4782386 | G19: 11643300 | H19: 557068 | I19: 339245 | J19: 7147045 | K19: 6497470 | L19: 1819276 | M19: -6470756 | N19: -12967819 | O19: -2412025 | P19: 1090845 | Q19: -3522937 | R19: 882337 | S19: 1508383 | T19: =O19+R19 -> -1529688 | U19: =K19+L19 -> 8316746 | V19: =IF(G19=0,"",F19/G19) -> 0.41074146 | W19: =IF(J19=0,"",(F19-G19)/J19) -> -0.95996513 | X19: =IF(E19=0,"",(I19/E19)*Days) -> 13.832329 | Y19: =IF(J19=0,"",T19/J19) -> -0.21403083 | Z19: =IF(E19=0,"",S19/E19) -> 0.16850028 | AA19: =IF(J19=0,"",E19/J19) -> 1.2525195 | AB19: =IF(U19=0,"",M19/J19) -> -0.90537502 | AC19: =IF(J19=0,"",U19/J19) -> 1.1636622 | AD19: =IF(J19=0,"",N19/J19) -> -1.8144309 | AE19: =IF(P19=0,"",O19/P19) -> -2.2111528 | AF19: =IF(P19=0,"N/A",S19/P19) -> 1.3827657 | AG19: =IF(U19=0,"",(S19/U19)) -> 0.18136697
B20: F03 | C20: =_xlfn.XLOOKUP(B20,Sector_Grouping!$A$4:$A$18,Sector_Grouping!$C$4:$C$18,"") -> Manufacturing Industry | D20: 2023 | E20: 2617189 | F20: 2321534 | G20: 15783128 | H20: =51293-3097 -> 48196 | I20: 169478 | J20: 2923896 | K20: 7492732 | L20: 63167 | M20: -13109808 | N20: -21111966 | O20: -1524323 | P20: 225310 | Q20: -2041388 | R20: 748267 | S20: 3803424 | T20: =O20+R20 -> -776056 | U20: =K20+L20 -> 7555899 | V20: =IF(G20=0,"",F20/G20) -> 0.1470896 | W20: =IF(J20=0,"",(F20-G20)/J20) -> -4.6039921 | X20: =IF(E20=0,"",(I20/E20)*Days) -> 23.635844 | Y20: =IF(J20=0,"",T20/J20) -> -0.26541847 | Z20: =IF(E20=0,"",S20/E20) -> 1.4532477 | AA20: =IF(J20=0,"",E20/J20) -> 0.89510331 | AB20: =IF(U20=0,"",M20/J20) -> -4.4836779 | AC20: =IF(J20=0,"",U20/J20) -> 2.5841887 | AD20: =IF(J20=0,"",N20/J20) -> -7.2204914 | AE20: =IF(P20=0,"",O20/P20) -> -6.7654476 | AF20: =IF(P20=0,"N/A",S20/P20) -> 16.880849 | AG20: =IF(U20=0,"",(S20/U20)) -> 0.50337147
B21: F04 | C21: =_xlfn.XLOOKUP(B21,Sector_Grouping!$A$4:$A$18,Sector_Grouping!$C$4:$C$18,"") -> Manufacturing Industry | D21: 2020 | E21: 3152811.5 | F21: 3271058.5 | G21: 2899882.9 | H21: 577428.6 | I21: 655687.72 | J21: 14800364 | K21: 1276473.4 | L21: 7659374.9 | M21: 4170078.7 | N21: 710668.62 | O21: -1030535.3 | P21: 149599 | Q21: -1200152 | R21: 668689.15 | S21: -25531.923 | T21: =O21+R21 -> -361846.15 | U21: =K21+L21 -> 8935848.3 | V21: =IF(G21=0,"",F21/G21) -> 1.1279968 | W21: =IF(J21=0,"",(F21-G21)/J21) -> 0.02507882 | X21: =IF(E21=0,"",(I21/E21)*Days) -> 75.908761 | Y21: =IF(J21=0,"",T21/J21) -> -0.024448463 | Z21: =IF(E21=0,"",S21/E21) -> -0.0080981443 | AA21: =IF(J21=0,"",E21/J21) -> 0.21302257 | AB21: =IF(U21=0,"",M21/J21) -> 0.28175515 | AC21: =IF(J21=0,"",U21/J21) -> 0.60375869 | AD21: =IF(J21=0,"",N21/J21) -> 0.04801697 | AE21: =IF(P21=0,"",O21/P21) -> -6.888651 | AF21: =IF(P21=0,"N/A",S21/P21) -> -0.17066908 | AG21: =IF(U21=0,"",(S21/U21)) -> -0.0028572467
B22: F04 | C22: =_xlfn.XLOOKUP(B22,Sector_Grouping!$A$4:$A$18,Sector_Grouping!$C$4:$C$18,"") -> Manufacturing Industry | D22: 2021 | E22: 3290433.6 | F22: 3534344.9 | G22: 6115955.3 | H22: 5271.742 | I22: =541992.662-4017.644 -> 537975.02 | J22: 17151029 | K22: 2438451.3 | L22: 8312706.2 | M22: 2575339.9 | N22: -489483.4 | O22: -881397.37 | P22: 751259.48 | Q22: -1596738.8 | R22: 1088804.5 | S22: 712717.05 | T22: =O22+R22 -> 207407.18 | U22: =K22+L22 -> 10751157 | V22: =IF(G22=0,"",F22/G22) -> 0.57788926 | W22: =IF(J22=0,"",(F22-G22)/J22) -> -0.15052219 | X22: =IF(E22=0,"",(I22/E22)*Days) -> 59.676294 | Y22: =IF(J22=0,"",T22/J22) -> 0.012092988 | Z22: =IF(E22=0,"",S22/E22) -> 0.21660278 | AA22: =IF(J22=0,"",E22/J22) -> 0.19185051 | AB22: =IF(U22=0,"",M22/J22) -> 0.15015658 | AC22: =IF(J22=0,"",U22/J22) -> 0.62685205 | AD22: =IF(J22=0,"",N22/J22) -> -0.028539594 | AE22: =IF(P22=0,"",O22/P22) -> -1.1732263 | AF22: =IF(P22=0,"N/A",S22/P22) -> 0.94869625 | AG22: =IF(U22=0,"",(S22/U22)) -> 0.066292123
B23: F04 | C23: =_xlfn.XLOOKUP(B23,Sector_Grouping!$A$4:$A$18,Sector_Grouping!$C$4:$C$18,"") -> Manufacturing Industry | D23: 2022 | E23: 3064464 | F23: 2810941.7 | G23: 6461338.6 | H23: 82989.953 | I23: =412275.654-18099.884 -> 394175.77 | J23: 14360760 | K23: 4251258.3 | L23: 7934317.1 | M23: -271923.32 | N23: -2084222.2 | O23: -2575222.2 | P23: 569554.55 | Q23: -3161052.5 | R23: 568810.33 | S23: -2679736.6 | T23: =O23+R23 -> -2006411.9 | U23: =K23+L23 -> 12185575 | V23: =IF(G23=0,"",F23/G23) -> 0.43504014 | W23: =IF(J23=0,"",(F23-G23)/J23) -> -0.25419247 | X23: =IF(E23=0,"",(I23/E23)*Days) -> 46.949207 | Y23: =IF(J23=0,"",T23/J23) -> -0.13971488 | Z23: =IF(E23=0,"",S23/E23) -> -0.87445523 | AA23: =IF(J23=0,"",E23/J23) -> 0.2133915 | AB23: =IF(U23=0,"",M23/J23) -> -0.018935162 | AC23: =IF(J23=0,"",U23/J23) -> 0.84853278 | AD23: =IF(J23=0,"",N23/J23) -> -0.14513314 | AE23: =IF(P23=0,"",O23/P23) -> -4.5214671 | AF23: =IF(P23=0,"N/A",S23/P23) -> -4.7049691 | AG23: =IF(U23=0,"",(S23/U23)) -> -0.21991055
B24: F04 | C24: =_xlfn.XLOOKUP(B24,Sector_Grouping!$A$4:$A$18,Sector_Grouping!$C$4:$C$18,"") -> Manufacturing Industry | D24: 2023 | E24: 2640653.5 | F24: 3184888 | G24: 6593920.8 | H24: 75541.459 | I24: =537884.072-92966.377 -> 444917.7 | J24: 18376201 | K24: 4282912 | L24: 7648728.5 | M24: 3862401.5 | N24: -2084222.2 | O24: -1750206.4 | P24: 2075642.2 | Q24: -3853239.2 | R24: 1133863 | S24: -2776744 | T24: =O24+R24 -> -616343.43 | U24: =K24+L24 -> 11931640 | V24: =IF(G24=0,"",F24/G24) -> 0.48300368 | W24: =IF(J24=0,"",(F24-G24)/J24) -> -0.18551347 | X24: =IF(E24=0,"",(I24/E24)*Days) -> 61.498019 | Y24: =IF(J24=0,"",T24/J24) -> -0.033540307 | Z24: =IF(E24=0,"",S24/E24) -> -1.0515367 | AA24: =IF(J24=0,"",E24/J24) -> 0.14369964 | AB24: =IF(U24=0,"",M24/J24) -> 0.21018498 | AC24: =IF(J24=0,"",U24/J24) -> 0.64929852 | AD24: =IF(J24=0,"",N24/J24) -> -0.11341964 | AE24: =IF(P24=0,"",O24/P24) -> -0.843212 | AF24: =IF(P24=0,"N/A",S24/P24) -> -1.3377759 | AG24: =IF(U24=0,"",(S24/U24)) -> -0.23272106
B25: F04 | C25: =_xlfn.XLOOKUP(B25,Sector_Grouping!$A$4:$A$18,Sector_Grouping!$C$4:$C$18,"") -> Manufacturing Industry | D25: 2024 | E25: 3275764.1 | F25: 4281350.1 | G25: 7508908.8 | H25: 203575.17 | I25: =102442.149-92966.377 -> 9475.772 | J25: 18444170 | K25: 4356093.3 | L25: 7853812.6 | M25: 2810298 | N25: -2084222.2 | O25: 314427.85 | P25: 1363161.9 | Q25: -1052103.5 | R25: 1082616.9 | S25: -301892.62 | T25: =O25+R25 -> 1397044.8 | U25: =K25+L25 -> 12209906 | V25: =IF(G25=0,"",F25/G25) -> 0.57016942 | W25: =IF(J25=0,"",(F25-G25)/J25) -> -0.17499072 | X25: =IF(E25=0,"",(I25/E25)*Days) -> 1.0558321 | Y25: =IF(J25=0,"",T25/J25) -> 0.075744519 | Z25: =IF(E25=0,"",S25/E25) -> -0.09215945 | AA25: =IF(J25=0,"",E25/J25) -> 0.17760431 | AB25: =IF(U25=0,"",M25/J25) -> 0.15236782 | AC25: =IF(J25=0,"",U25/J25) -> 0.6619927 | AD25: =IF(J25=0,"",N25/J25) -> -0.11300168 | AE25: =IF(P25=0,"",O25/P25) -> 0.23066068 | AF25: =IF(P25=0,"N/A",S25/P25) -> -0.22146498 | AG25: =IF(U25=0,"",(S25/U25)) -> -0.024725221
B26: F05 | C26: =_xlfn.XLOOKUP(B26,Sector_Grouping!$A$4:$A$18,Sector_Grouping!$C$4:$C$18,"") -> Agri-food Industry | D26: 2020 | E26: 2343424.5 | F26: 1978278.2 | G26: 1899610.5 | H26: 33153.605 | I26: 656362.03 | J26: 2733437.3 | K26: 1331326.4 | L26: 732189.67 | M26: 101637.16 | N26: -333483.34 | O26: -92535.984 | P26: 192303.21 | Q26: -249164.39 | R26: 129095.36 | S26: 245751.61 | T26: =O26+R26 -> 36559.374 | U26: =K26+L26 -> 2063516 | V26: =IF(G26=0,"",F26/G26) -> 1.0414126 | W26: =IF(J26=0,"",(F26-G26)/J26) -> 0.028779779 | X26: =IF(E26=0,"",(I26/E26)*Days) -> 102.23164 | Y26: =IF(J26=0,"",T26/J26) -> 0.013374872 | Z26: =IF(E26=0,"",S26/E26) -> 0.10486858 | AA26: =IF(J26=0,"",E26/J26) -> 0.85731781 | AB26: =IF(U26=0,"",M26/J26) -> 0.037182911 | AC26: =IF(J26=0,"",U26/J26) -> 0.75491617 | AD26: =IF(J26=0,"",N26/J26) -> -0.12200146 | AE26: =IF(P26=0,"",O26/P26) -> -0.48119833 | AF26: =IF(P26=0,"N/A",S26/P26) -> 1.2779382 | AG26: =IF(U26=0,"",(S26/U26)) -> 0.11909363
B27: F05 | C27: =_xlfn.XLOOKUP(B27,Sector_Grouping!$A$4:$A$18,Sector_Grouping!$C$4:$C$18,"") -> Agri-food Industry | D27: 2021 | E27: 2396446.6 | F27: 2116713.1 | G27: 1810298.1 | H27: 34569.112 | I27: 869494.84 | J27: 3609961.3 | K27: 340880.89 | L27: 1161020.8 | M27: 638642.42 | N27: -612440.07 | O27: 13563.594 | P27: 223370.66 | Q27: -152298.04 | R27: 185107.67 | S27: -229055.93 | T27: =O27+R27 -> 198671.26 | U27: =K27+L27 -> 1501901.7 | V27: =IF(G27=0,"",F27/G27) -> 1.1692622 | W27: =IF(J27=0,"",(F27-G27)/J27) -> 0.084880409 | X27: =IF(E27=0,"",(I27/E27)*Days) -> 132.43175 | Y27: =IF(J27=0,"",T27/J27) -> 0.055034181 | Z27: =IF(E27=0,"",S27/E27) -> -0.095581488 | AA27: =IF(J27=0,"",E27/J27) -> 0.66384274 | AB27: =IF(U27=0,"",M27/J27) -> 0.17691115 | AC27: =IF(J27=0,"",U27/J27) -> 0.41604371 | AD27: =IF(J27=0,"",N27/J27) -> -0.16965281 | AE27: =IF(P27=0,"",O27/P27) -> 0.060722362 | AF27: =IF(P27=0,"N/A",S27/P27) -> -1.0254522 | AG27: =IF(U27=0,"",(S27/U27)) -> -0.1525106
B28: F05 | C28: =_xlfn.XLOOKUP(B28,Sector_Grouping!$A$4:$A$18,Sector_Grouping!$C$4:$C$18,"") -> Agri-food Industry | D28: 2022 | E28: 2773679.7 | F28: 2455234.1 | G28: 2847537.2 | H28: 53158.713 | I28: 1021655.7 | J28: 3838744 | K28: 909848.94 | L28: 783003.58 | M28: 208203.16 | N28: -764738.11 | O28: -157229.61 | P28: 262580.28 | Q28: -430439.26 | R28: 154766.32 | S28: -54848.489 | T28: =O28+R28 -> -2463.287 | U28: =K28+L28 -> 1692852.5 | V28: =IF(G28=0,"",F28/G28) -> 0.86223071 | W28: =IF(J28=0,"",(F28-G28)/J28) -> -0.10219571 | X28: =IF(E28=0,"",(I28/E28)*Days) -> 134.4439 | Y28: =IF(J28=0,"",T28/J28) -> -0.00064169088 | Z28: =IF(E28=0,"",S28/E28) -> -0.01977463 | AA28: =IF(J28=0,"",E28/J28) -> 0.72254876 | AB28: =IF(U28=0,"",M28/J28) -> 0.054237313 | AC28: =IF(J28=0,"",U28/J28) -> 0.44099125 | AD28: =IF(J28=0,"",N28/J28) -> -0.19921571 | AE28: =IF(P28=0,"",O28/P28) -> -0.59878682 | AF28: =IF(P28=0,"N/A",S28/P28) -> -0.20888275 | AG28: =IF(U28=0,"",(S28/U28)) -> -0.03240004
B29: F05 | C29: =_xlfn.XLOOKUP(B29,Sector_Grouping!$A$4:$A$18,Sector_Grouping!$C$4:$C$18,"") -> Agri-food Industry | D29: 2023 | E29: 2689346.8 | F29: 2007725.6 | G29: 2846921.2 | H29: 65419.743 | I29: =889488.554-64806.237 -> 824682.32 | J29: 3279985.1 | K29: 1845077.4 | L29: 351970.51 | M29: 81093.353 | N29: -1156839 | O29: 94114.275 | P29: 252079.48 | Q29: -165448.13 | R29: 127213.28 | S29: 454493.72 | T29: =O29+R29 -> 221327.55 | U29: =K29+L29 -> 2197047.9 | V29: =IF(G29=0,"",F29/G29) -> 0.70522697 | W29: =IF(J29=0,"",(F29-G29)/J29) -> -0.25585348 | X29: =IF(E29=0,"",(I29/E29)*Days) -> 111.92645 | Y29: =IF(J29=0,"",T29/J29) -> 0.06747822 | Z29: =IF(E29=0,"",S29/E29) -> 0.16899781 | AA29: =IF(J29=0,"",E29/J29) -> 0.81992653 | AB29: =IF(U29=0,"",M29/J29) -> 0.024723696 | AC29: =IF(J29=0,"",U29/J29) -> 0.66983473 | AD29: =IF(J29=0,"",N29/J29) -> -0.35269644 | AE29: =IF(P29=0,"",O29/P29) -> 0.37335159 | AF29: =IF(P29=0,"N/A",S29/P29) -> 1.8029779 | AG29: =IF(U29=0,"",(S29/U29)) -> 0.20686564
B30: F05 | C30: =_xlfn.XLOOKUP(B30,Sector_Grouping!$A$4:$A$18,Sector_Grouping!$C$4:$C$18,"") -> Agri-food Industry | D30: 2024 | E30: 2496634 | F30: 2915230.3 | G30: 3354155.6 | H30: 1146010 | I30: =915034.236-64806.237 -> 850228 | J30: 4094750.2 | K30: 2031487.4 | L30: 120767.32 | M30: 619827.23 | N30: -1322287.2 | O30: 71776.714 | P30: 190706.82 | Q30: -111266.12 | R30: 93699.616 | S30: 476343.43 | T30: =O30+R30 -> 165476.33 | U30: =K30+L30 -> 2152254.7 | V30: =IF(G30=0,"",F30/G30) -> 0.86913986 | W30: =IF(J30=0,"",(F30-G30)/J30) -> -0.1071922 | X30: =IF(E30=0,"",(I30/E30)*Days) -> 124.30065 | Y30: =IF(J30=0,"",T30/J30) -> 0.040411826 | Z30: =IF(E30=0,"",S30/E30) -> 0.19079426 | AA30: =IF(J30=0,"",E30/J30) -> 0.60971582 | AB30: =IF(U30=0,"",M30/J30) -> 0.1513712 | AC30: =IF(J30=0,"",U30/J30) -> 0.5256132 | AD30: =IF(J30=0,"",N30/J30) -> -0.32292255 | AE30: =IF(P30=0,"",O30/P30) -> 0.37637205 | AF30: =IF(P30=0,"N/A",S30/P30) -> 2.4977788 | AG30: =IF(U30=0,"",(S30/U30)) -> 0.22132298
B31: F06 | C31: =_xlfn.XLOOKUP(B31,Sector_Grouping!$A$4:$A$18,Sector_Grouping!$C$4:$C$18,"") -> Manufacturing Industry | D31: 2021 | E31: 653881.62 | F31: 1471913 | G31: 18942.424 | H31: 862025.44 | I31: 303136.56 | J31: 4259632 | K31: 0 | L31: 1 | M31: 4240689.5 | N31: 0 | O31: -140626.53 | P31: 31516.061 | Q31: -109310.47 | R31: 59769.488 | S31: -49540.985 | T31: =O31+R31 -> -80857.046 | U31: =K31+L31 -> 1 | V31: =IF(G31=0,"",F31/G31) -> 77.704573 | W31: =IF(J31=0,"",(F31-G31)/J31) -> 0.34110237 | X31: =IF(E31=0,"",(I31/E31)*Days) -> 169.21235 | Y31: =IF(J31=0,"",T31/J31) -> -0.018982167 | Z31: =IF(E31=0,"",S31/E31) -> -0.075764456 | AA31: =IF(J31=0,"",E31/J31) -> 0.1535066 | AB31: =IF(U31=0,"",M31/J31) -> 0.99555304 | AC31: =IF(J31=0,"",U31/J31) -> 2.3476207e-07 | AD31: =IF(J31=0,"",N31/J31) -> 0 | AE31: =IF(P31=0,"",O31/P31) -> -4.4620593 | AF31: =IF(P31=0,"N/A",S31/P31) -> -1.5719282 | AG31: =IF(U31=0,"",(S31/U31)) -> -49540.985
B32: F06 | C32: =_xlfn.XLOOKUP(B32,Sector_Grouping!$A$4:$A$18,Sector_Grouping!$C$4:$C$18,"") -> Manufacturing Industry | D32: 2022 | E32: 3828155.2 | F32: 1513623.8 | G32: 666679.04 | H32: 225124.36 | I32: 409098.06 | J32: 4943848.9 | K32: 44058.533 | L32: 0 | M32: 4277169.8 | N32: -109310.47 | O32: 100398.29 | P32: 62989.694 | Q32: 36480.309 | R32: 110027.93 | S32: 30162.207 | T32: =O32+R32 -> 210426.22 | U32: =K32+L32 -> 44058.533 | V32: =IF(G32=0,"",F32/G32) -> 2.2703935 | W32: =IF(J32=0,"",(F32-G32)/J32) -> 0.17131282 | X32: =IF(E32=0,"",(I32/E32)*Days) -> 39.00594 | Y32: =IF(J32=0,"",T32/J32) -> 0.042563239 | Z32: =IF(E32=0,"",S32/E32) -> 0.0078790449 | AA32: =IF(J32=0,"",E32/J32) -> 0.77432691 | AB32: =IF(U32=0,"",M32/J32) -> 0.86514979 | AC32: =IF(J32=0,"",U32/J32) -> 0.008911788 | AD32: =IF(J32=0,"",N32/J32) -> -0.022110399 | AE32: =IF(P32=0,"",O32/P32) -> 1.5938843 | AF32: =IF(P32=0,"N/A",S32/P32) -> 0.47884352 | AG32: =IF(U32=0,"",(S32/U32)) -> 0.68459399
B33: F06 | C33: =_xlfn.XLOOKUP(B33,Sector_Grouping!$A$4:$A$18,Sector_Grouping!$C$4:$C$18,"") -> Manufacturing Industry | D33: 2023 | E33: 973049.91 | F33: 4234442.6 | G33: 538000.96 | H33: 3194740.6 | I33: 411634.91 | J33: 7665884.9 | K33: 8536.421 | L33: 850235.54 | M33: 6277648.4 | N33: -72830.164 | O33: -493308.15 | P33: 11928.244 | Q33: -499521.45 | R33: 230822.75 | S33: -60919.471 | T33: =O33+R33 -> -262485.4 | U33: =K33+L33 -> 858771.96 | V33: =IF(G33=0,"",F33/G33) -> 7.8706972 | W33: =IF(J33=0,"",(F33-G33)/J33) -> 0.48219374 | X33: =IF(E33=0,"",(I33/E33)*Days) -> 154.40805 | Y33: =IF(J33=0,"",T33/J33) -> -0.034240718 | Z33: =IF(E33=0,"",S33/E33) -> -0.062606728 | AA33: =IF(J33=0,"",E33/J33) -> 0.1269325 | AB33: =IF(U33=0,"",M33/J33) -> 0.81890721 | AC33: =IF(J33=0,"",U33/J33) -> 0.11202516 | AD33: =IF(J33=0,"",N33/J33) -> -0.0095005554 | AE33: =IF(P33=0,"",O33/P33) -> -41.35631 | AF33: =IF(P33=0,"N/A",S33/P33) -> -5.1071617 | AG33: =IF(U33=0,"",(S33/U33)) -> -0.070937891
B34: F06 | C34: =_xlfn.XLOOKUP(B34,Sector_Grouping!$A$4:$A$18,Sector_Grouping!$C$4:$C$18,"") -> Manufacturing Industry | D34: 2024 | E34: 1829785.1 | F34: 3398206.5 | G34: 476857.94 | H34: 231056.95 | I34: 1375632.2 | J34: 6909282.9 | K34: 9714.373 | L34: 840521.16 | M34: 5586143.8 | N34: -572351.61 | O34: -700708.53 | P34: 18378.109 | Q34: -691504.63 | R34: 242114.09 | S34: -2625970.9 | T34: =O34+R34 -> -458594.44 | U34: =K34+L34 -> 850235.54 | V34: =IF(G34=0,"",F34/G34) -> 7.1262451 | W34: =IF(J34=0,"",(F34-G34)/J34) -> 0.42281503 | X34: =IF(E34=0,"",(I34/E34)*Days) -> 274.40696 | Y34: =IF(J34=0,"",T34/J34) -> -0.066373668 | Z34: =IF(E34=0,"",S34/E34) -> -1.4351253 | AA34: =IF(J34=0,"",E34/J34) -> 0.26482996 | AB34: =IF(U34=0,"",M34/J34) -> 0.80849834 | AC34: =IF(J34=0,"",U34/J34) -> 0.12305699 | AD34: =IF(J34=0,"",N34/J34) -> -0.082838063 | AE34: =IF(P34=0,"",O34/P34) -> -38.127347 | AF34: =IF(P34=0,"N/A",S34/P34) -> -142.8858 | AG34: =IF(U34=0,"",(S34/U34)) -> -3.0885216
B35: F07 | C35: =_xlfn.XLOOKUP(B35,Sector_Grouping!$A$4:$A$18,Sector_Grouping!$C$4:$C$18,"") -> Services and Commerce | D35: 2020 | E35: 6512106 | F35: 7983504.5 | G35: 13086672 | H35: 59314.082 | I35: 3550877.5 | J35: 13815880 | K35: 9275637.9 | L35: 543407.42 | M35: 185800.29 | N35: -117126.17 | O35: -492580.28 | P35: 791983.56 | Q35: -1306847 | R35: 401209.99 | S35: 621357.44 | T35: =O35+R35 -> -91370.291 | U35: =K35+L35 -> 9819045.3 | V35: =IF(G35=0,"",F35/G35) -> 0.61004848 | W35: =IF(J35=0,"",(F35-G35)/J35) -> -0.36936972 | X35: =IF(E35=0,"",(I35/E35)*Days) -> 199.02475 | Y35: =IF(J35=0,"",T35/J35) -> -0.0066134254 | Z35: =IF(E35=0,"",S35/E35) -> 0.095415743 | AA35: =IF(J35=0,"",E35/J35) -> 0.47134935 | AB35: =IF(U35=0,"",M35/J35) -> 0.013448314 | AC35: =IF(J35=0,"",U35/J35) -> 0.7107072 | AD35: =IF(J35=0,"",N35/J35) -> -0.0084776484 | AE35: =IF(P35=0,"",O35/P35) -> -0.62195771 | AF35: =IF(P35=0,"N/A",S35/P35) -> 0.7845585 | AG35: =IF(U35=0,"",(S35/U35)) -> 0.06328084
B36: F07 | C36: =_xlfn.XLOOKUP(B36,Sector_Grouping!$A$4:$A$18,Sector_Grouping!$C$4:$C$18,"") -> Services and Commerce | D36: 2021 | E36: 10200456 | F36: 7232748.6 | G36: 8810607.1 | H36: 273376.45 | I36: 3375146 | J36: 10939341 | K36: 3721118 | L36: 2138052.1 | M36: -9317.822 | N36: -3563013.2 | O36: 173720.81 | P36: 945885.85 | Q36: 212907.47 | R36: 229002.91 | S36: 3335610.7 | T36: =O36+R36 -> 402723.72 | U36: =K36+L36 -> 5859170.2 | V36: =IF(G36=0,"",F36/G36) -> 0.82091376 | W36: =IF(J36=0,"",(F36-G36)/J36) -> -0.14423706 | X36: =IF(E36=0,"",(I36/E36)*Days) -> 120.77188 | Y36: =IF(J36=0,"",T36/J36) -> 0.036814256 | Z36: =IF(E36=0,"",S36/E36) -> 0.32700603 | AA36: =IF(J36=0,"",E36/J36) -> 0.93245616 | AB36: =IF(U36=0,"",M36/J36) -> -0.00085177175 | AC36: =IF(J36=0,"",U36/J36) -> 0.53560538 | AD36: =IF(J36=0,"",N36/J36) -> -0.32570638 | AE36: =IF(P36=0,"",O36/P36) -> 0.18365938 | AF36: =IF(P36=0,"N/A",S36/P36) -> 3.526441 | AG36: =IF(U36=0,"",(S36/U36)) -> 0.56929746
B37: F07 | C37: =_xlfn.XLOOKUP(B37,Sector_Grouping!$A$4:$A$18,Sector_Grouping!$C$4:$C$18,"") -> Services and Commerce | D37: 2022 | E37: 14456398 | F37: 10974618 | G37: 12313830 | H37: 748235.32 | I37: 5809577.2 | J37: 14627136 | K37: 9073588.9 | L37: 1703299.7 | M37: 196513.25 | N37: -3350105.8 | O37: 1330794.9 | P37: 1015349.1 | Q37: 205831.07 | R37: 191592.26 | S37: -4205927.5 | T37: =O37+R37 -> 1522387.1 | U37: =K37+L37 -> 10776889 | V37: =IF(G37=0,"",F37/G37) -> 0.89124326 | W37: =IF(J37=0,"",(F37-G37)/J37) -> -0.091556675 | X37: =IF(E37=0,"",(I37/E37)*Days) -> 146.68216 | Y37: =IF(J37=0,"",T37/J37) -> 0.10407964 | Z37: =IF(E37=0,"",S37/E37) -> -0.29093883 | AA37: =IF(J37=0,"",E37/J37) -> 0.98832731 | AB37: =IF(U37=0,"",M37/J37) -> 0.013434841 | AC37: =IF(J37=0,"",U37/J37) -> 0.73677365 | AD37: =IF(J37=0,"",N37/J37) -> -0.22903361 | AE37: =IF(P37=0,"",O37/P37) -> 1.3106772 | AF37: =IF(P37=0,"N/A",S37/P37) -> -4.1423463 | AG37: =IF(U37=0,"",(S37/U37)) -> -0.3902729
B38: F07 | C38: =_xlfn.XLOOKUP(B38,Sector_Grouping!$A$4:$A$18,Sector_Grouping!$C$4:$C$18,"") -> Services and Commerce | D38: 2023 | E38: 4007575.2 | F38: 7497180.5 | G38: 10396705 | H38: 1275613 | I38: 2456748.8 | J38: 11913920 | K38: 6392783.9 | L38: 1115538.8 | M38: 401676.69 | N38: -3144274.7 | O38: -620742.45 | P38: 992969.42 | Q38: -1909236.6 | R38: 169590.4 | S38: 1742891.6 | T38: =O38+R38 -> -451152.05 | U38: =K38+L38 -> 7508322.7 | V38: =IF(G38=0,"",F38/G38) -> 0.72111124 | W38: =IF(J38=0,"",(F38-G38)/J38) -> -0.2433728 | X38: =IF(E38=0,"",(I38/E38)*Days) -> 223.75458 | Y38: =IF(J38=0,"",T38/J38) -> -0.037867641 | Z38: =IF(E38=0,"",S38/E38) -> 0.43489929 | AA38: =IF(J38=0,"",E38/J38) -> 0.33637755 | AB38: =IF(U38=0,"",M38/J38) -> 0.033714906 | AC38: =IF(J38=0,"",U38/J38) -> 0.6302143 | AD38: =IF(J38=0,"",N38/J38) -> -0.26391605 | AE38: =IF(P38=0,"",O38/P38) -> -0.62513753 | AF38: =IF(P38=0,"N/A",S38/P38) -> 1.7552319 | AG38: =IF(U38=0,"",(S38/U38)) -> 0.23212796
B39: F07 | C39: =_xlfn.XLOOKUP(B39,Sector_Grouping!$A$4:$A$18,Sector_Grouping!$C$4:$C$18,"") -> Services and Commerce | D39: 2024 | E39: 9761652.9 | F39: 7098220.7 | G39: 8132092 | H39: 425074.43 | I39: 3271385.1 | J39: 11516166 | K39: 3942035.7 | L39: 3830000 | M39: -445925.86 | N39: -5050580.7 | O39: 403197.16 | P39: 1390658.1 | Q39: -850533.08 | R39: 43793.962 | S39: -1072401.2 | T39: =O39+R39 -> 446991.12 | U39: =K39+L39 -> 7772035.7 | V39: =IF(G39=0,"",F39/G39) -> 0.87286528 | W39: =IF(J39=0,"",(F39-G39)/J39) -> -0.089775647 | X39: =IF(E39=0,"",(I39/E39)*Days) -> 122.32104 | Y39: =IF(J39=0,"",T39/J39) -> 0.03881423 | Z39: =IF(E39=0,"",S39/E39) -> -0.10985856 | AA39: =IF(J39=0,"",E39/J39) -> 0.8476478 | AB39: =IF(U39=0,"",M39/J39) -> -0.038721729 | AC39: =IF(J39=0,"",U39/J39) -> 0.67488048 | AD39: =IF(J39=0,"",N39/J39) -> -0.43856442 | AE39: =IF(P39=0,"",O39/P39) -> 0.28993263 | AF39: =IF(P39=0,"N/A",S39/P39) -> -0.77114654 | AG39: =IF(U39=0,"",(S39/U39)) -> -0.13798202
B40: F08 | C40: =_xlfn.XLOOKUP(B40,Sector_Grouping!$A$4:$A$18,Sector_Grouping!$C$4:$C$18,"") -> Agri-food Industry | D40: 2020 | E40: 3329314 | F40: 2624021 | G40: 5855251 | H40: 66932 | I40: 1972494 | J40: 3390346 | K40: 2635442 | L40: 866554 | M40: -3331459 | N40: -3458556 | O40: -90813 | P40: 294432 | Q40: -388904 | R40: 133796 | S40: -280598 | T40: =O40+R40 -> 42983 | U40: =K40+L40 -> 3501996 | V40: =IF(G40=0,"",F40/G40) -> 0.44814834 | W40: =IF(J40=0,"",(F40-G40)/J40) -> -0.95306792 | X40: =IF(E40=0,"",(I40/E40)*Days) -> 216.24885 | Y40: =IF(J40=0,"",T40/J40) -> 0.012678057 | Z40: =IF(E40=0,"",S40/E40) -> -0.084281026 | AA40: =IF(J40=0,"",E40/J40) -> 0.9819983 | AB40: =IF(U40=0,"",M40/J40) -> -0.98263098 | AC40: =IF(J40=0,"",U40/J40) -> 1.0329317 | AD40: =IF(J40=0,"",N40/J40) -> -1.0201189 | AE40: =IF(P40=0,"",O40/P40) -> -0.30843455 | AF40: =IF(P40=0,"N/A",S40/P40) -> -0.95301462 | AG40: =IF(U40=0,"",(S40/U40)) -> -0.080125163
B41: F08 | C41: =_xlfn.XLOOKUP(B41,Sector_Grouping!$A$4:$A$18,Sector_Grouping!$C$4:$C$18,"") -> Agri-food Industry | D41: 2021 | E41: 4557050 | F41: 2388768 | G41: 5249574 | H41: 45150 | I41: 1240386 | J41: 3307648 | K41: 2536040 | L41: 1379285 | M41: -3321611 | N41: -3847459 | O41: 316250 | P41: 307823 | Q41: 9849 | R41: 151262 | S41: -131293 | T41: =O41+R41 -> 467512 | U41: =K41+L41 -> 3915325 | V41: =IF(G41=0,"",F41/G41) -> 0.45504035 | W41: =IF(J41=0,"",(F41-G41)/J41) -> -0.86490642 | X41: =IF(E41=0,"",(I41/E41)*Days) -> 99.349555 | Y41: =IF(J41=0,"",T41/J41) -> 0.14134273 | Z41: =IF(E41=0,"",S41/E41) -> -0.028810963 | AA41: =IF(J41=0,"",E41/J41) -> 1.3777312 | AB41: =IF(U41=0,"",M41/J41) -> -1.0042214 | AC41: =IF(J41=0,"",U41/J41) -> 1.1837188 | AD41: =IF(J41=0,"",N41/J41) -> -1.1632009 | AE41: =IF(P41=0,"",O41/P41) -> 1.0273761 | AF41: =IF(P41=0,"N/A",S41/P41) -> -0.42652109 | AG41: =IF(U41=0,"",(S41/U41)) -> -0.033533104
B42: F08 | C42: =_xlfn.XLOOKUP(B42,Sector_Grouping!$A$4:$A$18,Sector_Grouping!$C$4:$C$18,"") -> Agri-food Industry | D42: 2022 | E42: 6876189 | F42: 2567392 | G42: 4720394 | H42: 213263 | I42: 945703 | J42: 3664516 | K42: 1868797 | L42: 2370093 | M42: -3425971 | N42: -3895321 | O42: 349328 | P42: 382452 | Q42: -46650 | R42: 190488 | S42: 269557 | T42: =O42+R42 -> 539816 | U42: =K42+L42 -> 4238890 | V42: =IF(G42=0,"",F42/G42) -> 0.54389358 | W42: =IF(J42=0,"",(F42-G42)/J42) -> -0.58752697 | X42: =IF(E42=0,"",(I42/E42)*Days) -> 50.19955 | Y42: =IF(J42=0,"",T42/J42) -> 0.14730895 | Z42: =IF(E42=0,"",S42/E42) -> 0.039201511 | AA42: =IF(J42=0,"",E42/J42) -> 1.8764249 | AB42: =IF(U42=0,"",M42/J42) -> -0.93490409 | AC42: =IF(J42=0,"",U42/J42) -> 1.1567394 | AD42: =IF(J42=0,"",N42/J42) -> -1.0629838 | AE42: =IF(P42=0,"",O42/P42) -> 0.91339044 | AF42: =IF(P42=0,"N/A",S42/P42) -> 0.70481263 | AG42: =IF(U42=0,"",(S42/U42)) -> 0.063591412
... B44: F08 | C44: =_xlfn.XLOOKUP(B44,Sector_Grouping!$A$4:$A$18,Sector_Grouping!$C$4:$C$18,"") -> Agri-food Industry | D44: 2024 | E44: 8047553 | F44: 5256034 | G44: 4636233 | H44: 242486 | I44: 3387576 | J44: 6969508 | K44: 693267 | L44: 1677597 | M44: 655679 | N44: -3971899 | O44: 369488 | P44: 593870 | Q44: 111577 | R44: 171531 | S44: -873796 | T44: =O44+R44 -> 541019 | U44: =K44+L44 -> 2370864 | V44: =IF(G44=0,"",F44/G44) -> 1.1336863 | W44: =IF(J44=0,"",(F44-G44)/J44) -> 0.088930381 | X44: =IF(E44=0,"",(I44/E44)*Days) -> 153.64487 | Y44: =IF(J44=0,"",T44/J44) -> 0.07762657 | Z44: =IF(E44=0,"",S44/E44) -> -0.10857909 | AA44: =IF(J44=0,"",E44/J44) -> 1.1546802 | AB44: =IF(U44=0,"",M44/J44) -> 0.094078233 | AC44: =IF(J44=0,"",U44/J44) -> 0.34017667 | AD44: =IF(J44=0,"",N44/J44) -> -0.56989661 | AE44: =IF(P44=0,"",O44/P44) -> 0.62216984 | AF44: =IF(P44=0,"N/A",S44/P44) -> -1.4713591 | AG44: =IF(U44=0,"",(S44/U44)) -> -0.36855594
B45: F09 | C45: =_xlfn.XLOOKUP(B45,Sector_Grouping!$A$4:$A$18,Sector_Grouping!$C$4:$C$18,"") -> Manufacturing Industry | D45: 2019 | E45: 7832000 | F45: =4821000+750000+29000 -> 5600000 | G45: =1585000+1399000+147000 -> 3131000 | H45: 29000 | I45: 4821000 | J45: =F45+5790000 -> 11390000 | K45: 1399000 | L45: 126000 | M45: 2034000 | N45: -1235000 | O45: 1767000 | P45: 420000 | Q45: 1529000 | R45: 127000 | S45: 197000 | T45: =O45+R45 -> 1894000 | U45: =K45+L45 -> 1525000 | V45: =IF(G45=0,"",F45/G45) -> 1.788566 | W45: =IF(J45=0,"",(F45-G45)/J45) -> 0.2167691 | X45: =IF(E45=0,"",(I45/E45)*Days) -> 224.67633 | Y45: =IF(J45=0,"",T45/J45) -> 0.16628622 | Z45: =IF(E45=0,"",S45/E45) -> 0.025153218 | AA45: =IF(J45=0,"",E45/J45) -> 0.68762072 | AB45: =IF(U45=0,"",M45/J45) -> 0.1785777 | AC45: =IF(J45=0,"",U45/J45) -> 0.13388938 | AD45: =IF(J45=0,"",N45/J45) -> -0.10842845 | AE45: =IF(P45=0,"",O45/P45) -> 4.2071429 | AF45: =IF(P45=0,"N/A",S45/P45) -> 0.46904762 | AG45: =IF(U45=0,"",(S45/U45)) -> 0.12918033
B46: F09 | C46: =_xlfn.XLOOKUP(B46,Sector_Grouping!$A$4:$A$18,Sector_Grouping!$C$4:$C$18,"") -> Manufacturing Industry | D46: 2020 | E46: 4120000 | F46: =4971000+795000+341000 -> 6107000 | G46: =1611000+1240000+97000 -> 2948000 | H46: 341000 | I46: 4971000 | J46: =639000+F46 -> 6746000 | K46: 1140000 | L46: 1140000 | M46: 2067000 | N46: 293223 | O46: -328000 | P46: 265000 | Q46: -266000 | R46: 133000 | S46: -760000 | T46: =O46+R46 -> -195000 | U46: =K46+L46 -> 2280000 | V46: =IF(G46=0,"",F46/G46) -> 2.0715739 | W46: =IF(J46=0,"",(F46-G46)/J46) -> 0.4682775 | X46: =IF(E46=0,"",(I46/E46)*Days) -> 440.39199 | Y46: =IF(J46=0,"",T46/J46) -> -0.028906018 | Z46: =IF(E46=0,"",S46/E46) -> -0.18446602 | AA46: =IF(J46=0,"",E46/J46) -> 0.61073229 | AB46: =IF(U46=0,"",M46/J46) -> 0.30640379 | AC46: =IF(J46=0,"",U46/J46) -> 0.33797806 | AD46: =IF(J46=0,"",N46/J46) -> 0.043466202 | AE46: =IF(P46=0,"",O46/P46) -> -1.2377358 | AF46: =IF(P46=0,"N/A",S46/P46) -> -2.8679245 | AG46: =IF(U46=0,"",(S46/U46)) -> -0.33333333
B47: F09 | C47: =_xlfn.XLOOKUP(B47,Sector_Grouping!$A$4:$A$18,Sector_Grouping!$C$4:$C$18,"") -> Manufacturing Industry | D47: 2021 | E47: 6129893 | F47: 5869194 | G47: 3126643 | H47: 292832 | I47: 4640507 | J47: 7009901 | K47: 661782 | L47: 1110756 | M47: 2772501 | N47: 27223 | O47: 1141030 | P47: 321790 | Q47: 705278 | R47: 156248 | S47: 861526 | T47: =O47+R47 -> 1297278 | U47: =K47+L47 -> 1772538 | V47: =IF(G47=0,"",F47/G47) -> 1.8771551 | W47: =IF(J47=0,"",(F47-G47)/J47) -> 0.39123962 | X47: =IF(E47=0,"",(I47/E47)*Days) -> 276.3156 | Y47: =IF(J47=0,"",T47/J47) -> 0.18506367 | Z47: =IF(E47=0,"",S47/E47) -> 0.14054503 | AA47: =IF(J47=0,"",E47/J47) -> 0.87446214 | AB47: =IF(U47=0,"",M47/J47) -> 0.39551215 | AC47: =IF(J47=0,"",U47/J47) -> 0.25286206 | AD47: =IF(J47=0,"",N47/J47) -> 0.0038835071 | AE47: =IF(P47=0,"",O47/P47) -> 3.545884 | AF47: =IF(P47=0,"N/A",S47/P47) -> 2.6772926 | AG47: =IF(U47=0,"",(S47/U47)) -> 0.48604092
B48: F09 | C48: =_xlfn.XLOOKUP(B48,Sector_Grouping!$A$4:$A$18,Sector_Grouping!$C$4:$C$18,"") -> Manufacturing Industry | D48: 2022 | E48: 5215207 | F48: 7570731 | G48: 2630552 | H48: 1877433 | I48: 4589836 | J48: 10587893 | K48: 48134 | L48: 1251252 | M48: 6706089 | N48: 7237 | O48: -259234 | P48: 326863 | Q48: -491380 | R48: 264798 | S48: -204655 | T48: =O48+R48 -> 5564 | U48: =K48+L48 -> 1299386 | V48: =IF(G48=0,"",F48/G48) -> 2.8780009 | W48: =IF(J48=0,"",(F48-G48)/J48) -> 0.46658754 | X48: =IF(E48=0,"",(I48/E48)*Days) -> 321.23176 | Y48: =IF(J48=0,"",T48/J48) -> 0.00052550588 | Z48: =IF(E48=0,"",S48/E48) -> -0.039241971 | AA48: =IF(J48=0,"",E48/J48) -> 0.49256325 | AB48: =IF(U48=0,"",M48/J48) -> 0.63337333 | AC48: =IF(J48=0,"",U48/J48) -> 0.12272376 | AD48: =IF(J48=0,"",N48/J48) -> 0.00068351654 | AE48: =IF(P48=0,"",O48/P48) -> -0.7930968 | AF48: =IF(P48=0,"N/A",S48/P48) -> -0.62611859 | AG48: =IF(U48=0,"",(S48/U48)) -> -0.15750131
B49: F09 | C49: =_xlfn.XLOOKUP(B49,Sector_Grouping!$A$4:$A$18,Sector_Grouping!$C$4:$C$18,"") -> Manufacturing Industry | D49: 2023 | E49: 6195712 | F49: 5294198 | G49: 2997844 | H49: 514027 | I49: 3780584 | J49: 9541392 | K49: 1707722 | L49: 1244223 | M49: 5299326 | N49: -484143 | O49: -1058166 | P49: 469982 | Q49: -1394765 | R49: 276863 | S49: -74393 | T49: =O49+R49 -> -781303 | U49: =K49+L49 -> 2951945 | V49: =IF(G49=0,"",F49/G49) -> 1.7660018 | W49: =IF(J49=0,"",(F49-G49)/J49) -> 0.24067285 | X49: =IF(E49=0,"",(I49/E49)*Days) -> 222.72068 | Y49: =IF(J49=0,"",T49/J49) -> -0.081885641 | Z49: =IF(E49=0,"",S49/E49) -> -0.012007175 | AA49: =IF(J49=0,"",E49/J49) -> 0.64935095 | AB49: =IF(U49=0,"",M49/J49) -> 0.55540387 | AC49: =IF(J49=0,"",U49/J49) -> 0.30938305 | AD49: =IF(J49=0,"",N49/J49) -> -0.050741338 | AE49: =IF(P49=0,"",O49/P49) -> -2.2515032 | AF49: =IF(P49=0,"N/A",S49/P49) -> -0.15828904 | AG49: =IF(U49=0,"",(S49/U49)) -> -0.02520135
B50: F10 | C50: =_xlfn.XLOOKUP(B50,Sector_Grouping!$A$4:$A$18,Sector_Grouping!$C$4:$C$18,"") -> Manufacturing Industry | D50: 2020 | E50: 9833716.5 | F50: 16977163 | G50: 19192805 | H50: 312835.3 | I50: 6056954 | J50: 42138980 | K50: 12353140 | L50: 18537726 | M50: 4408448.6 | N50: -10377224 | O50: 465764.57 | P50: 3359514.6 | Q50: -2817839.2 | R50: 281331.85 | S50: 4073632.7 | T50: =O50+R50 -> 747096.42 | U50: =K50+L50 -> 30890866 | V50: =IF(G50=0,"",F50/G50) -> 0.88455871 | W50: =IF(J50=0,"",(F50-G50)/J50) -> -0.052579399 | X50: =IF(E50=0,"",(I50/E50)*Days) -> 224.81716 | Y50: =IF(J50=0,"",T50/J50) -> 0.017729343 | Z50: =IF(E50=0,"",S50/E50) -> 0.41425159 | AA50: =IF(J50=0,"",E50/J50) -> 0.23336389 | AB50: =IF(U50=0,"",M50/J50) -> 0.10461688 | AC50: =IF(J50=0,"",U50/J50) -> 0.73307105 | AD50: =IF(J50=0,"",N50/J50) -> -0.24626187 | AE50: =IF(P50=0,"",O50/P50) -> 0.13864044 | AF50: =IF(P50=0,"N/A",S50/P50) -> 1.2125658 | AG50: =IF(U50=0,"",(S50/U50)) -> 0.13187175
B51: F10 | C51: =_xlfn.XLOOKUP(B51,Sector_Grouping!$A$4:$A$18,Sector_Grouping!$C$4:$C$18,"") -> Manufacturing Industry | D51: 2021 | E51: 8133405.9 | F51: 21765181 | G51: 24006557 | H51: 5267912.1 | I51: 5361645.3 | J51: 47437544 | K51: 16953727 | L51: 17186094 | M51: 6244894 | N51: -13195063 | O51: -298462.67 | P51: 4214729.2 | Q51: -4210505.2 | R51: 63077.788 | S51: -3481423.6 | T51: =O51+R51 -> -235384.88 | U51: =K51+L51 -> 34139821 | V51: =IF(G51=0,"",F51/G51) -> 0.90663484 | W51: =IF(J51=0,"",(F51-G51)/J51) -> -0.04724899 | X51: =IF(E51=0,"",(I51/E51)*Days) -> 240.61267 | Y51: =IF(J51=0,"",T51/J51) -> -0.0049619954 | Z51: =IF(E51=0,"",S51/E51) -> -0.42804007 | AA51: =IF(J51=0,"",E51/J51) -> 0.17145504 | AB51: =IF(U51=0,"",M51/J51) -> 0.13164455 | AC51: =IF(J51=0,"",U51/J51) -> 0.71967934 | AD51: =IF(J51=0,"",N51/J51) -> -0.27815654 | AE51: =IF(P51=0,"",O51/P51) -> -0.070814198 | AF51: =IF(P51=0,"N/A",S51/P51) -> -0.82601361 | AG51: =IF(U51=0,"",(S51/U51)) -> -0.10197545
B52: F10 | C52: =_xlfn.XLOOKUP(B52,Sector_Grouping!$A$4:$A$18,Sector_Grouping!$C$4:$C$18,"") -> Manufacturing Industry | D52: 2022 | E52: 13772830 | F52: 19588853 | G52: 28984703 | H52: 1852410.2 | I52: 4888498.7 | J52: 44755093 | K52: 17632341 | L52: 17186094 | M52: -1415703.5 | N52: -17405568 | O52: -17583044 | P52: 3806308.9 | Q52: -7649746.9 | R52: 434965.46 | S52: -3231167.5 | T52: =O52+R52 -> -17148079 | U52: =K52+L52 -> 34818434 | V52: =IF(G52=0,"",F52/G52) -> 0.67583417 | W52: =IF(J52=0,"",(F52-G52)/J52) -> -0.20993924 | X52: =IF(E52=0,"",(I52/E52)*Days) -> 129.55231 | Y52: =IF(J52=0,"",T52/J52) -> -0.38315369 | Z52: =IF(E52=0,"",S52/E52) -> -0.23460447 | AA52: =IF(J52=0,"",E52/J52) -> 0.30773772 | AB52: =IF(U52=0,"",M52/J52) -> -0.031632233 | AC52: =IF(J52=0,"",U52/J52) -> 0.77797703 | AD52: =IF(J52=0,"",N52/J52) -> -0.38890698 | AE52: =IF(P52=0,"",O52/P52) -> -4.6194475 | AF52: =IF(P52=0,"N/A",S52/P52) -> -0.84889786 | AG52: =IF(U52=0,"",(S52/U52)) -> -0.092800482
B53: F10 | C53: =_xlfn.XLOOKUP(B53,Sector_Grouping!$A$4:$A$18,Sector_Grouping!$C$4:$C$18,"") -> Manufacturing Industry | D53: 2023 | E53: 7156845.6 | F53: 17934051 | G53: 14199381 | H53: 1784017 | I53: 3921882.5 | J53: 42005774 | K53: 7407337.5 | L53: 36679466 | M53: -8873073.3 | N53: -25746577 | O53: -2534429.8 | P53: 5214912.7 | Q53: -7686095.4 | R53: 522593.59 | S53: -8794040.9 | T53: =O53+R53 -> -2011836.2 | U53: =K53+L53 -> 44086803 | V53: =IF(G53=0,"",F53/G53) -> 1.2630164 | W53: =IF(J53=0,"",(F53-G53)/J53) -> 0.08890849 | X53: =IF(E53=0,"",(I53/E53)*Days) -> 200.01649 | Y53: =IF(J53=0,"",T53/J53) -> -0.047894278 | Z53: =IF(E53=0,"",S53/E53) -> -1.2287593 | AA53: =IF(J53=0,"",E53/J53) -> 0.17037766 | AB53: =IF(U53=0,"",M53/J53) -> -0.21123461 | AC53: =IF(J53=0,"",U53/J53) -> 1.0495415 | AD53: =IF(J53=0,"",N53/J53) -> -0.61292947 | AE53: =IF(P53=0,"",O53/P53) -> -0.4859966 | AF53: =IF(P53=0,"N/A",S53/P53) -> -1.6863256 | AG53: =IF(U53=0,"",(S53/U53)) -> -0.19947105
B54: F10 | C54: =_xlfn.XLOOKUP(B54,Sector_Grouping!$A$4:$A$18,Sector_Grouping!$C$4:$C$18,"") -> Manufacturing Industry | D54: 2024 | E54: 14757699 | F54: 19350702 | G54: 25297448 | H54: 1084315.2 | I54: 6320328.3 | J54: 43118556 | K54: 17140358 | L54: 31190633 | M54: -13369525 | N54: -33635001 | O54: 49243.334 | P54: 4533845.9 | Q54: -4294123.3 | R54: 507958.92 | S54: -4525429.9 | T54: =O54+R54 -> 557202.25 | U54: =K54+L54 -> 48330990 | V54: =IF(G54=0,"",F54/G54) -> 0.76492701 | W54: =IF(J54=0,"",(F54-G54)/J54) -> -0.13791619 | X54: =IF(E54=0,"",(I54/E54)*Days) -> 156.31975 | Y54: =IF(J54=0,"",T54/J54) -> 0.012922563 | Z54: =IF(E54=0,"",S54/E54) -> -0.30664874 | AA54: =IF(J54=0,"",E54/J54) -> 0.34225866 | AB54: =IF(U54=0,"",M54/J54) -> -0.31006431 | AC54: =IF(J54=0,"",U54/J54) -> 1.1208861 | AD54: =IF(J54=0,"",N54/J54) -> -0.78005861 | AE54: =IF(P54=0,"",O54/P54) -> 0.010861272 | AF54: =IF(P54=0,"N/A",S54/P54) -> -0.99814376 | AG54: =IF(U54=0,"",(S54/U54)) -> -0.093634124
B55: F11 | C55: =_xlfn.XLOOKUP(B55,Sector_Grouping!$A$4:$A$18,Sector_Grouping!$C$4:$C$18,"") -> Manufacturing Industry | D55: 2020 | E55: 2761865 | F55: 2094822 | G55: 5852933 | H55: 503179 | I55: 561481 | J55: 13446778 | K55: 727419 | L55: 7854875 | M55: -300876 | N55: -4764966 | O55: -3247860 | P55: 1183222 | Q55: -4435076 | R55: 1874848 | S55: 73335 | T55: =O55+R55 -> -1373012 | U55: =K55+L55 -> 8582294 | V55: =IF(G55=0,"",F55/G55) -> 0.35790979 | W55: =IF(J55=0,"",(F55-G55)/J55) -> -0.27948041 | X55: =IF(E55=0,"",(I55/E55)*Days) -> 74.203687 | Y55: =IF(J55=0,"",T55/J55) -> -0.10210714 | Z55: =IF(E55=0,"",S55/E55) -> 0.02655271 | AA55: =IF(J55=0,"",E55/J55) -> 0.20539233 | AB55: =IF(U55=0,"",M55/J55) -> -0.022375323 | AC55: =IF(J55=0,"",U55/J55) -> 0.63824167 | AD55: =IF(J55=0,"",N55/J55) -> -0.35435745 | AE55: =IF(P55=0,"",O55/P55) -> -2.7449287 | AF55: =IF(P55=0,"N/A",S55/P55) -> 0.061979071 | AG55: =IF(U55=0,"",(S55/U55)) -> 0.0085449182
B56: F11 | C56: =_xlfn.XLOOKUP(B56,Sector_Grouping!$A$4:$A$18,Sector_Grouping!$C$4:$C$18,"") -> Manufacturing Industry | D56: 2021 | E56: 5984926 | F56: 2844238 | G56: 9109647 | H56: 86542 | I56: 1792313 | J56: 13084154 | K56: 1928753 | L56: 7426739 | M56: -3931655 | N56: -14335268 | O56: -2822510 | P56: 796008 | Q56: -3630779 | R56: 1069627 | S56: -534564 | T56: =O56+R56 -> -1752883 | U56: =K56+L56 -> 9355492 | V56: =IF(G56=0,"",F56/G56) -> 0.31222264 | W56: =IF(J56=0,"",(F56-G56)/J56) -> -0.47885473 | X56: =IF(E56=0,"",(I56/E56)*Days) -> 109.30699 | Y56: =IF(J56=0,"",T56/J56) -> -0.13396992 | Z56: =IF(E56=0,"",S56/E56) -> -0.089318398 | AA56: =IF(J56=0,"",E56/J56) -> 0.45741788 | AB56: =IF(U56=0,"",M56/J56) -> -0.30048981 | AC56: =IF(J56=0,"",U56/J56) -> 0.7150246 | AD56: =IF(J56=0,"",N56/J56) -> -1.0956205 | AE56: =IF(P56=0,"",O56/P56) -> -3.5458312 | AF56: =IF(P56=0,"N/A",S56/P56) -> -0.67155606 | AG56: =IF(U56=0,"",(S56/U56)) -> -0.057139058
B57: F11 | C57: =_xlfn.XLOOKUP(B57,Sector_Grouping!$A$4:$A$18,Sector_Grouping!$C$4:$C$18,"") -> Manufacturing Industry | D57: 2022 | E57: 3798162 | F57: 1056189 | G57: 11879413 | H57: 6105 | I57: 259001 | J57: 10162557 | K57: 3724077 | L57: 6502513 | M57: -8576864 | N57: -14335268 | O57: -1507739 | P57: 1271599 | Q57: -4645209 | R57: 1017124 | S57: -242870 | T57: =O57+R57 -> -490615 | U57: =K57+L57 -> 10226590 | V57: =IF(G57=0,"",F57/G57) -> 0.088909191 | W57: =IF(J57=0,"",(F57-G57)/J57) -> -1.0650099 | X57: =IF(E57=0,"",(I57/E57)*Days) -> 24.889766 | Y57: =IF(J57=0,"",T57/J57) -> -0.048276728 | Z57: =IF(E57=0,"",S57/E57) -> -0.063944087 | AA57: =IF(J57=0,"",E57/J57) -> 0.37374078 | AB57: =IF(U57=0,"",M57/J57) -> -0.84396712 | AC57: =IF(J57=0,"",U57/J57) -> 1.0063009 | AD57: =IF(J57=0,"",N57/J57) -> -1.4105966 | AE57: =IF(P57=0,"",O57/P57) -> -1.1857032 | AF57: =IF(P57=0,"N/A",S57/P57) -> -0.19099575 | AG57: =IF(U57=0,"",(S57/U57)) -> -0.023748874
B58: F11 | C58: =_xlfn.XLOOKUP(B58,Sector_Grouping!$A$4:$A$18,Sector_Grouping!$C$4:$C$18,"") -> Manufacturing Industry | D58: 2023 | E58: 3198335.5 | F58: 5794514.3 | G58: 15683070 | H58: 38375.596 | I58: 1061859 | J58: 18449472 | K58: 2558684.4 | L58: 7628702.5 | M58: -5317602.3 | N58: -22611256 | O58: -641075.13 | P58: 1324410.7 | Q58: -1974283.8 | R58: 836789.15 | S58: 111656.87 | T58: =O58+R58 -> 195714.02 | U58: =K58+L58 -> 10187387 | V58: =IF(G58=0,"",F58/G58) -> 0.36947577 | W58: =IF(J58=0,"",(F58-G58)/J58) -> -0.53598041 | X58: =IF(E58=0,"",(I58/E58)*Days) -> 121.18133 | Y58: =IF(J58=0,"",T58/J58) -> 0.010608109 | Z58: =IF(E58=0,"",S58/E58) -> 0.034910931 | AA58: =IF(J58=0,"",E58/J58) -> 0.17335648 | AB58: =IF(U58=0,"",M58/J58) -> -0.28822517 | AC58: =IF(J58=0,"",U58/J58) -> 0.55217769 | AD58: =IF(J58=0,"",N58/J58) -> -1.2255774 | AE58: =IF(P58=0,"",O58/P58) -> -0.48404557 | AF58: =IF(P58=0,"N/A",S58/P58) -> 0.084306832 | AG58: =IF(U58=0,"",(S58/U58)) -> 0.010960305
... B67: F13 | C67: =_xlfn.XLOOKUP(B67,Sector_Grouping!$A$4:$A$18,Sector_Grouping!$C$4:$C$18,"") -> Services and Commerce | D67: 2022 | E67: 3576658 | F67: 427116 | G67: 4757712 | H67: 36052 | I67: 166368 | J67: 9853120 | K67: 1678707 | L67: 3900756 | M67: 594652 | N67: -2720161 | O67: 122945 | P67: 431439 | Q67: -325187 | R67: 380331 | S67: 2372769 | T67: =O67+R67 -> 503276 | U67: =K67+L67 -> 5579463 | V67: =IF(G67=0,"",F67/G67) -> 0.089773404 | W67: =IF(J67=0,"",(F67-G67)/J67) -> -0.4395152 | X67: =IF(E67=0,"",(I67/E67)*Days) -> 16.97795 | Y67: =IF(J67=0,"",T67/J67) -> 0.051077831 | Z67: =IF(E67=0,"",S67/E67) -> 0.66340394 | AA67: =IF(J67=0,"",E67/J67) -> 0.36299751 | AB67: =IF(U67=0,"",M67/J67) -> 0.060351645 | AC67: =IF(J67=0,"",U67/J67) -> 0.56626358 | AD67: =IF(J67=0,"",N67/J67) -> -0.27607103 | AE67: =IF(P67=0,"",O67/P67) -> 0.28496497 | AF67: =IF(P67=0,"N/A",S67/P67) -> 5.4996628 | AG67: =IF(U67=0,"",(S67/U67)) -> 0.42526835
B68: F13 | C68: =_xlfn.XLOOKUP(B68,Sector_Grouping!$A$4:$A$18,Sector_Grouping!$C$4:$C$18,"") -> Services and Commerce | D68: 2023 | E68: 4886274.8 | F68: 1930758.1 | G68: 3766662.2 | H68: 1242656.3 | I68: =408397.267-148073.341 -> 260323.93 | J68: 11167722 | K68: 338025.66 | L68: 1250000 | M68: 5551060.1 | N68: -3045349.4 | O68: -98144 | P68: 196636.25 | Q68: -43590.462 | R68: 34217.896 | S68: 203122.94 | T68: =O68+R68 -> -63926.104 | U68: =K68+L68 -> 1588025.7 | V68: =IF(G68=0,"",F68/G68) -> 0.51259125 | W68: =IF(J68=0,"",(F68-G68)/J68) -> -0.16439378 | X68: =IF(E68=0,"",(I68/E68)*Days) -> 19.445945 | Y68: =IF(J68=0,"",T68/J68) -> -0.0057241846 | Z68: =IF(E68=0,"",S68/E68) -> 0.041570101 | AA68: =IF(J68=0,"",E68/J68) -> 0.43753549 | AB68: =IF(U68=0,"",M68/J68) -> 0.49706287 | AC68: =IF(J68=0,"",U68/J68) -> 0.14219781 | AD68: =IF(J68=0,"",N68/J68) -> -0.27269208 | AE68: =IF(P68=0,"",O68/P68) -> -0.49911447 | AF68: =IF(P68=0,"N/A",S68/P68) -> 1.0329883 | AG68: =IF(U68=0,"",(S68/U68)) -> 0.1279091
B69: F13 | C69: =_xlfn.XLOOKUP(B69,Sector_Grouping!$A$4:$A$18,Sector_Grouping!$C$4:$C$18,"") -> Services and Commerce | D69: 2024 | E69: 5505637.5 | F69: 1617866.4 | G69: 3957223.2 | H69: 547483.21 | I69: =386883.018-148073.341 -> 238809.68 | J69: 11134270 | K69: 284362.78 | L69: 1218750 | M69: 5358296.5 | N69: -3088939.9 | O69: -44744.802 | P69: 152264.02 | Q69: -192763.57 | R69: 34178.919 | S69: 10948.75 | T69: =O69+R69 -> -10565.883 | U69: =K69+L69 -> 1503112.8 | V69: =IF(G69=0,"",F69/G69) -> 0.40883882 | W69: =IF(J69=0,"",(F69-G69)/J69) -> -0.21010419 | X69: =IF(E69=0,"",(I69/E69)*Days) -> 15.832051 | Y69: =IF(J69=0,"",T69/J69) -> -0.0009489516 | Z69: =IF(E69=0,"",S69/E69) -> 0.0019886434 | AA69: =IF(J69=0,"",E69/J69) -> 0.49447675 | AB69: =IF(U69=0,"",M69/J69) -> 0.48124365 | AC69: =IF(J69=0,"",U69/J69) -> 0.13499878 | AD69: =IF(J69=0,"",N69/J69) -> -0.27742636 | AE69: =IF(P69=0,"",O69/P69) -> -0.29386325 | AF69: =IF(P69=0,"N/A",S69/P69) -> 0.071906348 | AG69: =IF(U69=0,"",(S69/U69)) -> 0.0072840509
B70: F14 | C70: =_xlfn.XLOOKUP(B70,Sector_Grouping!$A$4:$A$18,Sector_Grouping!$C$4:$C$18,"") -> Manufacturing Industry | D70: 2020 | E70: 1129000 | F70: =4137000-1020000 -> 3117000 | G70: 2021000 | H70: 186000 | I70: 1370000 | J70: 4137000 | K70: 1328000 | L70: 444000 | M70: 950000 | N70: -359000 | O70: 540000 | P70: 165000 | Q70: 409000 | R70: 283000 | S70: 225000 | T70: =O70+R70 -> 823000 | U70: =K70+L70 -> 1772000 | V70: =IF(G70=0,"",F70/G70) -> 1.5423058 | W70: =IF(J70=0,"",(F70-G70)/J70) -> 0.26492628 | X70: =IF(E70=0,"",(I70/E70)*Days) -> 442.91408 | Y70: =IF(J70=0,"",T70/J70) -> 0.19893643 | Z70: =IF(E70=0,"",S70/E70) -> 0.19929141 | AA70: =IF(J70=0,"",E70/J70) -> 0.27290307 | AB70: =IF(U70=0,"",M70/J70) -> 0.229635 | AC70: =IF(J70=0,"",U70/J70) -> 0.42832971 | AD70: =IF(J70=0,"",N70/J70) -> -0.086777858 | AE70: =IF(P70=0,"",O70/P70) -> 3.2727273 | AF70: =IF(P70=0,"N/A",S70/P70) -> 1.3636364 | AG70: =IF(U70=0,"",(S70/U70)) -> 0.12697517
B71: F14 | C71: =_xlfn.XLOOKUP(B71,Sector_Grouping!$A$4:$A$18,Sector_Grouping!$C$4:$C$18,"") -> Manufacturing Industry | D71: 2021 | E71: 1554000 | F71: =6093000-1302000 -> 4791000 | G71: 1831000 | H71: 691000 | I71: 598000 | J71: 6093000 | K71: 1217000 | L71: 636000 | M71: 2873000 | N71: 47000 | O71: 738000 | P71: 298000 | Q71: 524000 | R71: 318000 | S71: -5757000 | T71: =O71+R71 -> 1056000 | U71: =K71+L71 -> 1853000 | V71: =IF(G71=0,"",F71/G71) -> 2.6166029 | W71: =IF(J71=0,"",(F71-G71)/J71) -> 0.48580338 | X71: =IF(E71=0,"",(I71/E71)*Days) -> 140.45689 | Y71: =IF(J71=0,"",T71/J71) -> 0.17331364 | Z71: =IF(E71=0,"",S71/E71) -> -3.7046332 | AA71: =IF(J71=0,"",E71/J71) -> 0.25504677 | AB71: =IF(U71=0,"",M71/J71) -> 0.4715247 | AC71: =IF(J71=0,"",U71/J71) -> 0.30411948 | AD71: =IF(J71=0,"",N71/J71) -> 0.0077137699 | AE71: =IF(P71=0,"",O71/P71) -> 2.4765101 | AF71: =IF(P71=0,"N/A",S71/P71) -> -19.318792 | AG71: =IF(U71=0,"",(S71/U71)) -> -3.1068538
B72: F14 | C72: =_xlfn.XLOOKUP(B72,Sector_Grouping!$A$4:$A$18,Sector_Grouping!$C$4:$C$18,"") -> Manufacturing Industry | D72: 2022 | E72: 2027239 | F72: 5967006 | G72: 2607304 | H72: 797346 | I72: 1450413 | J72: 8058237 | K72: 1782000 | L72: 513458 | M72: 4136545 | N72: 542444 | O72: 1090012 | P72: 287699 | Q72: 896073 | R72: 424888 | S72: 5128053 | T72: =O72+R72 -> 1514900 | U72: =K72+L72 -> 2295458 | V72: =IF(G72=0,"",F72/G72) -> 2.2885732 | W72: =IF(J72=0,"",(F72-G72)/J72) -> 0.41692767 | X72: =IF(E72=0,"",(I72/E72)*Days) -> 261.14373 | Y72: =IF(J72=0,"",T72/J72) -> 0.18799397 | Z72: =IF(E72=0,"",S72/E72) -> 2.529575 | AA72: =IF(J72=0,"",E72/J72) -> 0.25157351 | AB72: =IF(U72=0,"",M72/J72) -> 0.51333127 | AC72: =IF(J72=0,"",U72/J72) -> 0.28485859 | AD72: =IF(J72=0,"",N72/J72) -> 0.067315469 | AE72: =IF(P72=0,"",O72/P72) -> 3.7887236 | AF72: =IF(P72=0,"N/A",S72/P72) -> 17.824369 | AG72: =IF(U72=0,"",(S72/U72)) -> 2.2339999
B73: F14 | C73: =_xlfn.XLOOKUP(B73,Sector_Grouping!$A$4:$A$18,Sector_Grouping!$C$4:$C$18,"") -> Manufacturing Industry | D73: 2023 | E73: 3087120 | F73: 6382090 | G73: 3961416 | H73: 343615 | I73: 1777523 | J73: 11759745 | K73: 2211000 | L73: 1623436 | M73: 4464280 | N73: 1335241 | O73: 192485 | P73: 431771 | Q73: 27735 | R73: 509197 | S73: 2153974 | T73: =O73+R73 -> 701682 | U73: =K73+L73 -> 3834436 | V73: =IF(G73=0,"",F73/G73) -> 1.6110628 | W73: =IF(J73=0,"",(F73-G73)/J73) -> 0.20584409 | X73: =IF(E73=0,"",(I73/E73)*Days) -> 210.16219 | Y73: =IF(J73=0,"",T73/J73) -> 0.059668131 | Z73: =IF(E73=0,"",S73/E73) -> 0.69772928 | AA73: =IF(J73=0,"",E73/J73) -> 0.2625159 | AB73: =IF(U73=0,"",M73/J73) -> 0.37962388 | AC73: =IF(J73=0,"",U73/J73) -> 0.32606455 | AD73: =IF(J73=0,"",N73/J73) -> 0.11354336 | AE73: =IF(P73=0,"",O73/P73) -> 0.44580345 | AF73: =IF(P73=0,"N/A",S73/P73) -> 4.9886954 | AG73: =IF(U73=0,"",(S73/U73)) -> 0.56174467
B74: F14 | C74: =_xlfn.XLOOKUP(B74,Sector_Grouping!$A$4:$A$18,Sector_Grouping!$C$4:$C$18,"") -> Manufacturing Industry | D74: 2024 | E74: 3046303 | F74: 12207303 | G74: 5322338 | H74: 410268 | I74: 2086654 | J74: 18260191 | K74: 2374745 | L74: 1641775 | M74: 8908941 | N74: 1294827 | O74: -11512 | P74: 575463 | Q74: -355339 | R74: 661877 | S74: -3737166 | T74: =O74+R74 -> 650365 | U74: =K74+L74 -> 4016520 | V74: =IF(G74=0,"",F74/G74) -> 2.2935979 | W74: =IF(J74=0,"",(F74-G74)/J74) -> 0.37704781 | X74: =IF(E74=0,"",(I74/E74)*Days) -> 250.01739 | Y74: =IF(J74=0,"",T74/J74) -> 0.03561655 | Z74: =IF(E74=0,"",S74/E74) -> -1.2267874 | AA74: =IF(J74=0,"",E74/J74) -> 0.16682755 | AB74: =IF(U74=0,"",M74/J74) -> 0.48788871 | AC74: =IF(J74=0,"",U74/J74) -> 0.21996046 | AD74: =IF(J74=0,"",N74/J74) -> 0.070909828 | AE74: =IF(P74=0,"",O74/P74) -> -0.020004761 | AF74: =IF(P74=0,"N/A",S74/P74) -> -6.4941899 | AG74: =IF(U74=0,"",(S74/U74)) -> -0.93044875
B75: F15 | C75: =_xlfn.XLOOKUP(B75,Sector_Grouping!$A$4:$A$18,Sector_Grouping!$C$4:$C$18,"") -> Manufacturing Industry | D75: 2020 | E75: 527000 | F75: 522000 | G75: 1293000 | H75: 22984 | I75: 48663 | J75: 10685000 | K75: 150583 | L75: 5462000 | M75: 3930000 | N75: 0 | O75: -528000 | P75: 658422 | Q75: -500983 | R75: 469000 | S75: -31983 | T75: =O75+R75 -> -59000 | U75: =K75+L75 -> 5612583 | V75: =IF(G75=0,"",F75/G75) -> 0.4037123 | W75: =IF(J75=0,"",(F75-G75)/J75) -> -0.07215723 | X75: =IF(E75=0,"",(I75/E75)*Days) -> 33.703975 | Y75: =IF(J75=0,"",T75/J75) -> -0.0055217595 | Z75: =IF(E75=0,"",S75/E75) -> -0.060688805 | AA75: =IF(J75=0,"",E75/J75) -> 0.049321479 | AB75: =IF(U75=0,"",M75/J75) -> 0.36780533 | AC75: =IF(J75=0,"",U75/J75) -> 0.52527684 | AD75: =IF(J75=0,"",N75/J75) -> 0 | AE75: =IF(P75=0,"",O75/P75) -> -0.80191731 | AF75: =IF(P75=0,"N/A",S75/P75) -> -0.04857523 | AG75: =IF(U75=0,"",(S75/U75)) -> -0.0056984458
B76: F15 | C76: =_xlfn.XLOOKUP(B76,Sector_Grouping!$A$4:$A$18,Sector_Grouping!$C$4:$C$18,"") -> Manufacturing Industry | D76: 2021 | E76: 669000 | F76: 1109000 | G76: 1963000 | H76: 38952 | I76: 65874 | J76: 11532000 | K76: 199582 | L76: 6823000 | M76: 2746000 | N76: 0 | O76: -844000 | P76: 800595 | Q76: -1080000 | R76: 546000 | S76: -445494 | T76: =O76+R76 -> -298000 | U76: =K76+L76 -> 7022582 | V76: =IF(G76=0,"",F76/G76) -> 0.5649516 | W76: =IF(J76=0,"",(F76-G76)/J76) -> -0.074054804 | X76: =IF(E76=0,"",(I76/E76)*Days) -> 35.940224 | Y76: =IF(J76=0,"",T76/J76) -> -0.025841138 | Z76: =IF(E76=0,"",S76/E76) -> -0.66591031 | AA76: =IF(J76=0,"",E76/J76) -> 0.058012487 | AB76: =IF(U76=0,"",M76/J76) -> 0.23812001 | AC76: =IF(J76=0,"",U76/J76) -> 0.60896479 | AD76: =IF(J76=0,"",N76/J76) -> 0 | AE76: =IF(P76=0,"",O76/P76) -> -1.0542159 | AF76: =IF(P76=0,"N/A",S76/P76) -> -0.55645364 | AG76: =IF(U76=0,"",(S76/U76)) -> -0.063437351
B77: F15 | C77: =_xlfn.XLOOKUP(B77,Sector_Grouping!$A$4:$A$18,Sector_Grouping!$C$4:$C$18,"") -> Manufacturing Industry | D77: 2022 | E77: 723987 | F77: 3174136 | G77: 3435719 | H77: 43560 | I77: 82224 | J77: 11395666 | K77: 215945 | L77: 6643965 | M77: 1315982 | N77: -533523 | O77: -1274550 | P77: 1160385 | Q77: -2324890 | R77: 771756 | S77: -1546135 | T77: =O77+R77 -> -502794 | U77: =K77+L77 -> 6859910 | V77: =IF(G77=0,"",F77/G77) -> 0.92386368 | W77: =IF(J77=0,"",(F77-G77)/J77) -> -0.022954604 | X77: =IF(E77=0,"",(I77/E77)*Days) -> 41.453452 | Y77: =IF(J77=0,"",T77/J77) -> -0.044121511 | Z77: =IF(E77=0,"",S77/E77) -> -2.1355839 | AA77: =IF(J77=0,"",E77/J77) -> 0.063531785 | AB77: =IF(U77=0,"",M77/J77) -> 0.11548092 | AC77: =IF(J77=0,"",U77/J77) -> 0.60197535 | AD77: =IF(J77=0,"",N77/J77) -> -0.046818062 | AE77: =IF(P77=0,"",O77/P77) -> -1.0983854 | AF77: =IF(P77=0,"N/A",S77/P77) -> -1.3324328 | AG77: =IF(U77=0,"",(S77/U77)) -> -0.22538707
B78: F15 | C78: =_xlfn.XLOOKUP(B78,Sector_Grouping!$A$4:$A$18,Sector_Grouping!$C$4:$C$18,"") -> Manufacturing Industry | D78: 2023 | E78: 1065527.5 | F78: 2847847.6 | G78: 4746805.6 | H78: 1129827.9 | I78: 186532.82 | J78: 12275437 | K78: 406166.13 | L78: 6542346.7 | M78: 986284.17 | N78: -2086656.4 | O78: -1630224.1 | P78: 942635.49 | Q78: -2672065.9 | R78: 671413.64 | S78: -1606135.5 | T78: =O78+R78 -> -958810.49 | U78: =K78+L78 -> 6948512.8 | V78: =IF(G78=0,"",F78/G78) -> 0.59995033 | W78: =IF(J78=0,"",(F78-G78)/J78) -> -0.15469577 | X78: =IF(E78=0,"",(I78/E78)*Days) -> 63.897443 | Y78: =IF(J78=0,"",T78/J78) -> -0.078108057 | Z78: =IF(E78=0,"",S78/E78) -> -1.5073619 | AA78: =IF(J78=0,"",E78/J78) -> 0.086801594 | AB78: =IF(U78=0,"",M78/J78) -> 0.080346159 | AC78: =IF(J78=0,"",U78/J78) -> 0.56605016 | AD78: =IF(J78=0,"",N78/J78) -> -0.16998633 | AE78: =IF(P78=0,"",O78/P78) -> -1.7294322 | AF78: =IF(P78=0,"N/A",S78/P78) -> -1.7038776 | AG78: =IF(U78=0,"",(S78/U78)) -> -0.2311481
B79: F15 | C79: =_xlfn.XLOOKUP(B79,Sector_Grouping!$A$4:$A$18,Sector_Grouping!$C$4:$C$18,"") -> Manufacturing Industry | D79: 2024 | E79: 1965598.2 | F79: 2415905.2 | G79: 7939202.9 | H79: 7602.009 | I79: 464620.19 | J79: 10987731 | K79: 577083.74 | L79: 5454173.5 | M79: -2405645.4 | N79: -3886311.5 | O79: -1893364.6 | P79: 1325900.3 | Q79: -3234297.5 | R79: 752329.52 | S79: -2559601.4 | T79: =O79+R79 -> -1141035.1 | U79: =K79+L79 -> 6031257.3 | V79: =IF(G79=0,"",F79/G79) -> 0.30430073 | W79: =IF(J79=0,"",(F79-G79)/J79) -> -0.50267864 | X79: =IF(E79=0,"",(I79/E79)*Days) -> 86.27723 | Y79: =IF(J79=0,"",T79/J79) -> -0.10384629 | Z79: =IF(E79=0,"",S79/E79) -> -1.3021997 | AA79: =IF(J79=0,"",E79/J79) -> 0.17889028 | AB79: =IF(U79=0,"",M79/J79) -> -0.21893924 | AC79: =IF(J79=0,"",U79/J79) -> 0.54890835 | AD79: =IF(J79=0,"",N79/J79) -> -0.35369555 | AE79: =IF(P79=0,"",O79/P79) -> -1.4279842 | AF79: =IF(P79=0,"N/A",S79/P79) -> -1.930463 | AG79: =IF(U79=0,"",(S79/U79)) -> -0.42438935
C80: =_xlfn.XLOOKUP(B80,Sector_Grouping!$A$4:$A$18,Sector_Grouping!$C$4:$C$18,"")

Sheet Formula_Dictionary
A1: Formula Dictionary
A3: Pillar | B3: Indicator | C3: Formula | D3: Economic Interpretation
A4: Liquidity | B4: Current Ratio | C4: Current Assets / Current Liabilities | D4: Shows the SME’s ability to cover its short-term obligations using its current assets.
A5: Liquidity | B5: Working Capital / Total Assets | C5: (Current Assets - Current liabilities ) / Total Assets | D5: Shows the SME’s ability to maintain short-term financial stability.
A6: Liquidity | B6: Receivables Days | C6: (Accounts receivables / Sales ) * 365 | D6: Shows how quickly the SME can recover cash from customers and avoid liquidity stress.
A7: Cash Generation | B7: EBITDA / Total Assets | C7: EBITDA / Total Assets | D7: Shows the SME’s capacity to generate operating earnings from its asset base.
A8: Cash Generation | B8: CFO / Revenue | C8: CFO / Revenue | D8: Shows the SME’s ability to transform sales into cash, strengthening resilience.
A9: Cash Generation | B9: Asset Turnover | C9: Revenue/Total Assets | D9: Shows how efficiently the SME uses its assets to support activity and continuity.
A10: Capital Structure | B10: Equity Ratio | C10: Equity / Total Assets | D10: Shows the SME’s level of financial autonomy and reliance on its own capital.
A11: Capital Structure | B11: Financial Debt / Total Assets | C11: Total Financial Debt / Total Assets | D11: Shows the SME’s overall reliance on financial debt to finance its assets.
A12: Capital Structure | B12: Retained Earnings / Total Assets | C12: Retained Earnings / Total Assets | D12: Shows the SME’s ability to finance itself using accumulated profits.
A13: Debt Sustainability | B13: Interest Coverage Ratio (ICR) | C13: EBIT / Interest Expense | D13: Shows the SME’s ability to pay interest from its operating earnings.
A14: Debt Sustainability | B14: CFO / Interest Coverage | C14: CFO / Interest Expense | D14: Shows the SME’s ability to cover interest payments using operating cash flow.
A15: Debt Sustainability | B15: CFO / Financial Debt | C15: CFO / Total Financial Debt | D15: Shows the SME’s ability to repay financial debt using operating cash flow.

Sheet Sector_Grouping
A1: Sector_Grouping_Table
A3: Firm | B3: Original_Sector | C3: Grouped_Sector
A4: F01 | B4: Restauration rapide | C4: Services and Commerce
A5: F02 | B5: La transformation du poisson | C5: Agri-food Industry
A6: F03 | B6: Emballage alimentaire | C6: Manufacturing Industry
A7: F04 | B7: Emballage en plastique | C7: Manufacturing Industry
A8: F05 | B8: Agroalimentaire | C8: Agri-food Industry
A9: F06 | B9: Découpe Papier/carton | C9: Manufacturing Industry
A10: F07 | B10: Commerce et distribution papier | C10: Services and Commerce
A11: F08 | B11: Secteur de l’industrie agroalimentaire | C11: Agri-food Industry
A12: F09 | B12: Industrie 4.0 | C12: Manufacturing Industry
A13: F10 | B13: Industrie manufacturière | C13: Manufacturing Industry
A14: F11 | B14: Marché du fibrociment | C14: Manufacturing Industry
... A18: F15 | B18: Pharmaceutique | C18: Manufacturing Industry
A28: Reference category for regression: Industrial / Manufacturing / Materials

Sheet FRI Results
A1: Final FRI Results by Firm-Year
A3: Firm | B3: Year | C3: P1 Liq. | D3: P2 Cash | E3: P3 Cap. | F3: P4 Debt | G3: FRI Score | H3: Category | I3: FRI Change | J3: Trend
A4: F01 | B4: 2020 | C4: 60.09 | D4: 69.69 | E4: 83.26 | F4: 44.89 | G4: 64.48 | H4: High Resilience | I4: N/A | J4: N/A
A5: F01 | B5: 2021 | C5: 63.74 | D5: 75.35 | E5: 82.06 | F5: 58.08 | G5: 69.81 | H5: High Resilience | I5: 5.33 | J5: Improved
A6: F01 | B6: 2022 | C6: 65.63 | D6: 94.11 | E6: 83.42 | F6: 74.96 | G6: 79.53 | H6: High Resilience | I6: 9.72 | J6: Improved
A7: F01 | B7: 2023 | C7: 65.98 | D7: 87.72 | E7: 90.24 | F7: 92.67 | G7: 84.15 | H7: High Resilience | I7: 4.62 | J7: Improved
A8: F01 | B8: 2024 | C8: 62.87 | D8: 93.46 | E8: 91.95 | F8: 100 | G8: 87.07 | H8: High Resilience | I8: 2.92 | J8: Improved
A9: F02 | B9: 2020 | C9: 42.24 | D9: 41.02 | E9: 71.39 | F9: 40.92 | G9: 48.89 | H9: Medium Resilience | I9: N/A | J9: N/A | N9: Chart : Yearly FRI Evolution Across Firms
A10: F02 | B10: 2021 | C10: 53.43 | D10: 71.06 | E10: 70.06 | F10: 72.08 | G10: 66.66 | H10: Medium Resilience | I10: 17.77 | J10: Improved
A11: F02 | B11: 2022 | C11: 49.32 | D11: 42.13 | E11: 77.39 | F11: 29.73 | G11: 49.64 | H11: Medium Resilience | I11: -17.02 | J11: Deteriorated
A12: F02 | B12: 2023 | C12: 53.19 | D12: 81.51 | E12: 68.43 | F12: 57.18 | G12: 65.08 | H12: Medium Resilience | I12: 15.44 | J12: Improved
A13: F02 | B13: 2024 | C13: 53.62 | D13: 99.46 | E13: 74.4 | F13: 86.23 | G13: 78.43 | H13: Medium Resilience | I13: 13.35 | J13: Improved
A14: F03 | B14: 2019 | C14: 43.47 | D14: 41.85 | E14: 42.64 | F14: 36.55 | G14: 41.13 | H14: Low Resilience | I14: N/A | J14: N/A
A15: F03 | B15: 2020 | C15: 32.34 | D15: 62.54 | E15: 21.05 | F15: 53.01 | G15: 42.24 | H15: Low Resilience | I15: 1.11 | J15: Improved
A16: F03 | B16: 2021 | C16: 49.97 | D16: 31.53 | E16: 35.9 | F16: 17.28 | G16: 33.67 | H16: Low Resilience | I16: -8.57 | J16: Deteriorated
A17: F03 | B17: 2022 | C17: 25.69 | D17: 62.69 | E17: 15.79 | F17: 63.24 | G17: 41.85 | H17: Low Resilience | I17: 8.18 | J17: Improved
A18: F03 | B18: 2023 | C18: 29.62 | D18: 58.49 | E18: 23.05 | F18: 74.09 | G18: 46.31 | H18: Low Resilience | I18: 4.46 | J18: Improved
A19: F04 | B19: 2020 | C19: 65.33 | D19: 44.6 | E19: 76.18 | F19: 44.02 | G19: 57.53 | H19: Low Resilience | I19: N/A | J19: N/A
A20: F04 | B20: 2021 | C20: 50.72 | D20: 53.08 | E20: 70.73 | F20: 61.74 | G20: 59.07 | H20: Low Resilience | I20: 1.54 | J20: Improved
A21: F04 | B21: 2022 | C21: 46.05 | D21: 12.31 | E21: 57.21 | F21: 27.11 | G21: 35.67 | H21: Low Resilience | I21: -23.4 | J21: Deteriorated
A22: F04 | B22: 2023 | C22: 47.44 | D22: 18.16 | E22: 69.55 | F22: 47.69 | G22: 45.71 | H22: Low Resilience | I22: 10.04 | J22: Improved
A23: F04 | B23: 2024 | C23: 55.56 | D23: 52.91 | E23: 67.82 | F23: 59.45 | G23: 58.94 | H23: Low Resilience | I23: 13.23 | J23: Improved
A24: F05 | B24: 2020 | C24: 60.31 | D24: 71.09 | E24: 62 | F24: 66.01 | G24: 64.85 | H24: High Resilience | I24: N/A | J24: N/A
A25: F05 | B25: 2021 | C25: 60.76 | D25: 65.38 | E25: 74.98 | F25: 53.17 | G25: 63.57 | H25: High Resilience | I25: -1.28 | J25: Deteriorated
A26: F05 | B26: 2022 | C26: 48.09 | D26: 62.61 | E26: 70.7 | F26: 57.06 | G26: 59.61 | H26: High Resilience | I26: -3.96 | J26: Deteriorated
A27: F05 | B27: 2023 | C27: 42.71 | D27: 77.46 | E27: 59.38 | F27: 72.24 | G27: 62.95 | H27: High Resilience | I27: 3.34 | J27: Improved
A28: F05 | B28: 2024 | C28: 49.38 | D28: 68.48 | E28: 67.55 | F28: 74.87 | G28: 65.07 | H28: High Resilience | I28: 2.12 | J28: Improved
A29: F06 | B29: 2021 | C29: 94.66 | D29: 41.89 | E29: 100 | F29: 18.98 | G29: 63.88 | H29: High Resilience | I29: N/A | J29: N/A
A30: F06 | B30: 2022 | C30: 97.42 | D30: 69.67 | E30: 99.52 | F30: 80.22 | G30: 86.71 | H30: High Resilience | I30: 22.83 | J30: Improved | T30: Source: Author’s analysis using Python
A31: F06 | B31: 2023 | C31: 99.94 | D31: 39.65 | E31: 99.79 | F31: 26.26 | G31: 66.41 | H31: High Resilience | I31: -20.3 | J31: Deteriorated
A32: F06 | B32: 2024 | C32: 83.64 | D32: 9.62 | E32: 98.19 | F32: 0 | G32: 47.86 | H32: High Resilience | I32: -18.55 | J32: Deteriorated
A33: F07 | B33: 2020 | C33: 25.5 | D33: 56.82 | E33: 65.33 | F33: 62.63 | G33: 52.57 | H33: Medium Resilience | I33: N/A | J33: N/A
A34: F07 | B34: 2021 | C34: 47.63 | D34: 80.99 | E34: 63.65 | F34: 86.31 | G34: 69.64 | H34: Medium Resilience | I34: 17.07 | J34: Improved
A35: F07 | B35: 2022 | C35: 47.41 | D35: 76.46 | E35: 59.69 | F35: 40.45 | G35: 56 | H35: Medium Resilience | I35: -13.64 | J35: Deteriorated
A36: F07 | B36: 2023 | C36: 39.74 | D36: 59.76 | E36: 62.79 | F36: 70.02 | G36: 58.08 | H36: Medium Resilience | I36: 2.08 | J36: Improved
A37: F07 | B37: 2024 | C37: 51.31 | D37: 68.86 | E37: 68.87 | F37: 78.98 | G37: 67 | H37: Medium Resilience | I37: 8.92 | J37: Improved
A38: F08 | B38: 2020 | C38: 0 | D38: 70.61 | E38: 9.92 | F38: 54.23 | G38: 33.69 | H38: Low Resilience | I38: N/A | J38: N/A
A39: F08 | B39: 2021 | C39: 18.54 | D39: 97.52 | E39: 2.78 | F39: 60.72 | G39: 44.89 | H39: Low Resilience | I39: 11.2 | J39: Improved
A40: F08 | B40: 2022 | C40: 36.27 | D40: 99.71 | E40: 6.15 | F40: 66.53 | G40: 52.17 | H40: Low Resilience | I40: 7.28 | J40: Improved
A41: F08 | B41: 2023 | C41: 31.95 | D41: 100 | E41: 11.41 | F41: 65.06 | G41: 52.1 | H41: Low Resilience | I41: -0.07 | J41: Deteriorated
A42: F08 | B42: 2024 | C42: 57.42 | D42: 82.65 | E42: 66.73 | F42: 47.81 | G42: 63.65 | H42: Low Resilience | I42: 11.55 | J42: Improved
A43: F09 | B43: 2019 | C43: 65.21 | D43: 81.31 | E43: 85.33 | F43: 73.79 | G43: 76.41 | H43: High Resilience | I43: N/A | J43: N/A
A44: F09 | B44: 2020 | C44: 69.48 | D44: 52.33 | E44: 85.11 | F44: 39.12 | G44: 61.51 | H44: High Resilience | I44: -14.9 | J44: Deteriorated
A45: F09 | B45: 2021 | C45: 66.15 | D45: 89.88 | E45: 89.02 | F45: 89.94 | G45: 83.75 | H45: High Resilience | I45: 22.24 | J45: Improved
A46: F09 | B46: 2022 | C46: 81.85 | D46: 55.27 | E46: 98.6 | F46: 72.03 | G46: 76.94 | H46: High Resilience | I46: -6.81 | J46: Deteriorated
A47: F09 | B47: 2023 | C47: 75.85 | D47: 71.41 | E47: 89.73 | F47: 72.93 | G47: 77.48 | H47: High Resilience | I47: 0.54 | J47: Improved
A48: F10 | B48: 2020 | C48: 38.35 | D48: 59.4 | E48: 61.54 | F48: 67.8 | G48: 56.77 | H48: Low Resilience | I48: N/A | J48: N/A
A49: F10 | B49: 2021 | C49: 36.88 | D49: 36.15 | E49: 61.89 | F49: 54.73 | G49: 47.41 | H49: Low Resilience | I49: -9.36 | J49: Deteriorated
A50: F10 | B50: 2022 | C50: 41.4 | D50: 24.78 | E50: 53.84 | F50: 42.58 | G50: 40.65 | H50: Low Resilience | I50: -6.76 | J50: Deteriorated
A51: F10 | B51: 2023 | C51: 53.84 | D51: 33.41 | E51: 56.14 | F51: 48.36 | G51: 47.94 | H51: Low Resilience | I51: 7.29 | J51: Improved
A52: F10 | B52: 2024 | C52: 62.09 | D52: 46.09 | E52: 67.94 | F52: 58.6 | G52: 58.68 | H52: Low Resilience | I52: 10.74 | J52: Improved
A53: F11 | B53: 2020 | C53: 40.1 | D53: 36.41 | E53: 59.26 | F53: 53.16 | G53: 47.23 | H53: Low Resilience | I53: N/A | J53: N/A
A54: F11 | B54: 2021 | C54: 27.74 | D54: 37.95 | E54: 34.18 | F54: 46.95 | G54: 36.71 | H54: Low Resilience | I54: -10.52 | J54: Deteriorated
A55: F11 | B55: 2022 | C55: 22.46 | D55: 45.6 | E55: 8.08 | F55: 55.74 | G55: 32.97 | H55: Low Resilience | I55: -3.74 | J55: Deteriorated
A56: F11 | B56: 2023 | C56: 25.32 | D56: 48.29 | E56: 36.81 | F56: 59.41 | G56: 42.46 | H56: Low Resilience | I56: 9.49 | J56: Improved
A57: F11 | B57: 2024 | C57: 24.73 | D57: 0 | E57: 44.95 | F57: 2.79 | G57: 18.12 | H57: Low Resilience | I57: -24.34 | J57: Deteriorated
A58: F12 | B58: 2020 | C58: 91.21 | D58: 64.19 | E58: 79.32 | F58: 52.77 | G58: 71.87 | H58: Medium Resilience | I58: N/A | J58: N/A
A59: F12 | B59: 2021 | C59: 83.91 | D59: 64.74 | E59: 79.19 | F59: 59.67 | G59: 71.88 | H59: Medium Resilience | I59: 0.01 | J59: Improved
A60: F12 | B60: 2022 | C60: 52.64 | D60: 37.81 | E60: 75.4 | F60: 66.25 | G60: 58.03 | H60: Medium Resilience | I60: -13.85 | J60: Deteriorated
A61: F12 | B61: 2023 | C61: 46.75 | D61: 41.18 | E61: 64.07 | F61: 56.18 | G61: 52.04 | H61: Medium Resilience | I61: -5.99 | J61: Deteriorated
A62: F12 | B62: 2024 | C62: 38.64 | D62: 13.2 | E62: 64.99 | F62: 43.48 | G62: 40.08 | H62: Medium Resilience | I62: -11.96 | J62: Deteriorated
A63: F13 | B63: 2020 | C63: 0 | D63: 79.18 | E63: 9.92 | F63: 58.08 | G63: 36.79 | H63: Medium Resilience | I63: N/A | J63: N/A
A64: F13 | B64: 2021 | C64: 18.53 | D64: 97.52 | E64: 2.78 | F64: 60.72 | G64: 44.89 | H64: Medium Resilience | I64: 8.1 | J64: Improved
A65: F13 | B65: 2022 | C65: 41.17 | D65: 69.36 | E65: 65.17 | F65: 88.42 | G65: 66.03 | H65: Medium Resilience | I65: 21.14 | J65: Improved
A66: F13 | B66: 2023 | C66: 54.27 | D66: 54.69 | E66: 88.86 | F66: 65.39 | G66: 65.8 | H66: Medium Resilience | I66: -0.23 | J66: Deteriorated
A67: F13 | B67: 2024 | C67: 51.15 | D67: 56.08 | E67: 88.62 | F67: 59.79 | G67: 63.91 | H67: Medium Resilience | I67: -1.89 | J67: Deteriorated
A68: F14 | B68: 2020 | C68: 53.23 | D68: 72.79 | E68: 77.62 | F68: 76.65 | G68: 70.07 | H68: High Resilience | I68: N/A | J68: N/A
A69: F14 | B69: 2021 | C69: 100 | D69: 35.19 | E69: 89.23 | F69: 22.23 | G69: 61.66 | H69: High Resilience | I69: -8.41 | J69: Deteriorated
A70: F14 | B70: 2022 | C70: 77.03 | D70: 79.18 | E70: 92.12 | F70: 100 | G70: 87.08 | H70: High Resilience | I70: 25.42 | J70: Improved
A71: F14 | B71: 2023 | C71: 63.29 | D71: 67.25 | E71: 88.37 | F71: 91.7 | G71: 77.65 | H71: High Resilience | I71: -9.43 | J71: Deteriorated
A72: F14 | B72: 2024 | C72: 77.22 | D72: 22.74 | E72: 93.67 | F72: 56.1 | G72: 62.43 | H72: High Resilience | I72: -15.22 | J72: Deteriorated
A73: F15 | B73: 2020 | C73: 53.45 | D73: 42.49 | E73: 79.62 | F73: 57.7 | G73: 58.32 | H73: Medium Resilience | I73: N/A | J73: N/A
A74: F15 | B74: 2021 | C74: 56.22 | D74: 26.7 | E74: 73.96 | F74: 53.91 | G74: 52.7 | H74: Medium Resilience | I74: -5.62 | J74: Deteriorated
A75: F15 | B75: 2022 | C75: 64.24 | D75: 6.9 | E75: 70.32 | F75: 47.21 | G75: 47.17 | H75: Medium Resilience | I75: -5.53 | J75: Deteriorated
A76: F15 | B76: 2023 | C76: 65.45 | D76: 33.08 | E76: 73.96 | F76: 50.14 | G76: 55.66 | H76: Medium Resilience | I76: 8.49 | J76: Improved
A77: F15 | B77: 2024 | C77: 69.89 | D77: 40.74 | E77: 77.56 | F77: 52.37 | G77: 60.14 | H77: Medium Resilience | I77: 4.48 | J77: Improved

Sheet FRI by Firm
A1: FRI Per Firm
A3: Firm | B3: N | C3: Mean FRI | D3: Median FRI | E3: Std Dev | F3: Min FRI | G3: Max FRI | H3: Resilience Category
A4: F01 | B4: 5 | C4: 77.01 | D4: 79.53 | E4: 9.58 | F4: 64.48 | G4: 87.07 | H4: High Resilience
A5: F02 | B5: 5 | C5: 61.74 | D5: 65.08 | E5: 12.5 | F5: 48.89 | G5: 78.43 | H5: Medium Resilience
A6: F03 | B6: 5 | C6: 41.04 | D6: 41.85 | E6: 4.59 | F6: 33.67 | G6: 46.31 | H6: Low Resilience
A7: F04 | B7: 5 | C7: 51.38 | D7: 57.53 | E7: 10.41 | F7: 35.67 | G7: 59.07 | H7: Low Resilience
A8: F05 | B8: 5 | C8: 63.21 | D8: 63.57 | E8: 2.2 | F8: 59.61 | G8: 65.07 | H8: High Resilience
A9: F06 | B9: 4 | C9: 66.22 | D9: 65.14 | E9: 15.94 | F9: 47.86 | G9: 86.71 | H9: High Resilience
A10: F07 | B10: 5 | C10: 60.66 | D10: 58.08 | E10: 7.33 | F10: 52.57 | G10: 69.64 | H10: Medium Resilience
A11: F08 | B11: 5 | C11: 49.3 | D11: 52.1 | E11: 11.01 | F11: 33.69 | G11: 63.65 | H11: Low Resilience
A12: F09 | B12: 5 | C12: 75.22 | D12: 76.94 | E12: 8.22 | F12: 61.51 | G12: 83.75 | H12: High Resilience
A13: F10 | B13: 5 | C13: 50.29 | D13: 47.94 | E13: 7.4 | F13: 40.65 | G13: 58.68 | H13: Low Resilience
A14: F11 | B14: 5 | C14: 35.5 | D14: 36.71 | E14: 11.14 | F14: 18.12 | G14: 47.23 | H14: Low Resilience
A15: F12 | B15: 5 | C15: 58.78 | D15: 58.03 | E15: 13.59 | F15: 40.08 | G15: 71.88 | H15: Medium Resilience
... A18: F15 | B18: 5 | C18: 54.8 | D18: 55.66 | E18: 5.11 | F18: 47.17 | G18: 60.14 | H18: Medium Resilience

Sheet Pillar_CorrelationAnalysis
A1: Within-Pillar Correlation Matrices
A2: Red>0.85 (redundant) | Yellow 0.70-0.85 | Green<0.30 (weak signal)
A3: P1 Liquidity | F3: Within the Liquidity pillar, Current Ratio and WC/Total Assets are moderately correlated (ρ = 0.823), indicating that both variables reflect short-term financial strength. However, the correlation remains below the 0.85 redundancy threshold, suggesting that each indicator still provides additional information. Receivables Days shows weaker and negative correlations with the other liquidity measures, meaning that it captures a different aspect of liquidity related to collection efficiency rather than available short-term resources. Overall, the indicators are sufficiently related without being redundant, which supports their aggregation through PCA into a single Liquidity score for the resilience index.
B4: current_ratio | C4: wc_total_assets | D4: receivables_days
A5: current_ratio | B5: 1 | C5: 0.823 | D5: -0.58
A6: wc_total_assets | B6: 0.823 | C6: 1 | D6: -0.494
A7: receivables_days | B7: -0.58 | C7: -0.494 | D7: 1
A10: P2 Cash Generation | F10: Within the Cash Generation pillar, correlations between the indicators remain relatively weak (ranging from 0.283 to 0.404), suggesting limited overlap between the measures. EBITDA/Total Assets reflects operating profitability relative to the asset base, CFO/Revenue captures the conversion of revenue into actual cash flow, and Asset Turnover measures how efficiently assets generate sales. Since each indicator captures a different dimension of cash generation capacity, retaining all three variables adds complementary information. This supports their aggregation through PCA into a single Cash Generation score for the resilience index.
B11: ebitda_total_assets | C11: cfo_revenue | D11: asset_turnover
A12: ebitda_total_assets | B12: 1 | C12: 0.283 | D12: 0.358
A13: cfo_revenue | B13: 0.283 | C13: 1 | D13: 0.404
A14: asset_turnover | B14: 0.358 | C14: 0.404 | D14: 1
A17: P3 Capital Structure | F17: Within the Capital Structure pillar, correlations are generally higher than in the other pillars. Equity Ratio and Financial Debt/Total Assets are strongly correlated (ρ = 0.890), reflecting the inverse relationship between equity and debt financing. Equity Ratio is also closely related to Retained Earnings/Total Assets (ρ = 0.836), since retained profits contribute to equity growth over time. Although some overlap exists between the indicators, PCA helps capture their shared information without double-counting, supporting their aggregation into a single Capital Structure score.
B18: equity_ratio | C18: financial_debt_total_assets | D18: retained_earnings_total_assets
A19: equity_ratio | B19: 1 | C19: 0.89 | D19: 0.836
A20: financial_debt_total_assets | B20: 0.89 | C20: 1 | D20: 0.715
A21: retained_earnings_total_assets | B21: 0.836 | C21: 0.715 | D21: 1
A24: P4 Debt Sustainability | F24: Within the Debt Sustainability pillar, ICR shows relatively weak correlations with the other indicators (0.429 and 0.410), suggesting that it captures a distinct aspect of debt sustainability related to interest repayment capacity. In contrast, CFO/Interest Coverage and CFO/Financial Debt are more strongly correlated (ρ = 0.895), reflecting their common focus on the ability of operating cash flow to support debt obligations. Overall, the indicators remain economically complementary and can therefore be aggregated through PCA into a single Debt Sustainability score.
B25: icr | C25: cfo_interest_coverage | D25: cfo_financial_debt
A26: icr | B26: 1 | C26: 0.429 | D26: 0.41
A27: cfo_interest_coverage | B27: 0.429 | C27: 1 | D27: 0.895
A28: cfo_financial_debt | B28: 0.41 | C28: 0.895 | D28: 1

Sheet PCA_Diagnostic 
A1: PCA Diagnostics — KMO, Variance & Loadings
A2: KMO values above 0.60 and PC1 explained variance above 40% indicate acceptable PCA adequacy.
A3: PCA LOG — Overview
A4: pillar | B4: kmo | C4: kmo_interpretation | D4: pc1_var_pct | E4: pc2_var_pct | F4: pc3_var_pct | G4: eigenvalue_pc1 | H4: orientation_corr | I4: flipped | J4: n_obs
A5: P1_Liquidity | B5: 0.643 | C5: Good | D5: 75.86 | E5: 18.48 | F5: 5.66 | G5: 2.3071 | H5: 0.9951 | I5: No | J5: 74
A6: P2_Cash_Generation | B6: 0.63 | C6: Good | D6: 56.64 | E6: 24.06 | F6: 19.3 | G6: 1.7225 | H6: 0.9996 | I6: No | J6: 74
A7: P3_Capital_Structure | B7: 0.669 | C7: Good | D7: 87.65 | E7: 9.65 | F7: 2.69 | G7: 2.6656 | H7: 1 | I7: No | J7: 74
A8: P4_Debt_Sustainability | B8: 0.594 | C8: Acceptable | D8: 73.01 | E8: 23.49 | F8: 3.5 | G8: 2.2204 | H8: 0.9962 | I8: No | J8: 74
A11: PC1 LOADINGS | F11: PC1 Loadings by Pillar
A12: pillar | B12: indicator | C12: pc1_loading
A13: P1_Liquidity | B13: current_ratio | C13: 0.6177
A14: P1_Liquidity | B14: wc_total_assets | C14: 0.5968
A15: P1_Liquidity | B15: receivables_days | C15: -0.5122
A16: P2_Cash_Generation | B16: ebitda_total_assets | C16: 0.5452
A17: P2_Cash_Generation | B17: cfo_revenue | C17: 0.5737
A18: P2_Cash_Generation | B18: asset_turnover | C18: 0.6112
A19: P3_Capital_Structure | B19: equity_ratio | C19: 0.5997
A20: P3_Capital_Structure | B20: financial_debt_total_assets | C20: 0.5727
A21: P3_Capital_Structure | B21: retained_earnings_total_assets | C21: 0.5589
A22: P4_Debt_Sustainability | B22: icr | C22: 0.4461
A23: P4_Debt_Sustainability | B23: cfo_interest_coverage | C23: 0.6349
A24: P4_Debt_Sustainability | B24: cfo_financial_debt | C24: 0.6308
G33: Source: Author’s analysis using Python

Sheet FRI_Visualizations
A1: FRI Visualizations
C5: Chart 1: FRI Score Distribution | AM5: Chart 2 : FRI Heatmap Firm x Year
D24: Source: Author’s analysis using Python | AL24: Source: Author’s analysis using Python
D27: Chart 3 : Pillar Score Boxplots | AM27: Chart 4 : Yearly FRI Evolution Across Firms
D45: Source: Author’s analysis using Python | AM45: Source: Author’s analysis using Python

Sheet Descriptives
A1: Descriptive Statistics and Normality Assessment
A3: variable | B3: n | C3: mean | D3: median | E3: std | F3: skew | G3: kurtosis | H3: shapiro_W | I3: shapiro_p | J3: normal
A4: Delta_FRI | B4: 59 | C4: 0.86 | D4: 1.54 | E4: 11.93 | F4: -0.09 | G4: -0.52 | H4: 0.99 | I4: 0.8253 | J4: Yes
A5: ROA | B5: 74 | C5: -0.1 | D5: -0.07 | E5: 0.15 | F5: -1.45 | G5: 3.26 | H5: 0.9 | I5: 0 | J5: No
A6: Net_Margin | B6: 74 | C6: -0.4 | D6: -0.15 | E6: 0.64 | F6: -2.12 | G6: 5.45 | H6: 0.77 | I6: 0 | J6: No
A7: EBITDA_Margin | B7: 74 | C7: -0.07 | D7: 0.01 | E7: 0.33 | F7: -0.75 | G7: 2.64 | H7: 0.9 | I7: 0 | J7: No
A8: FRI_score | B8: 74 | C8: 58.05 | D8: 58.81 | E8: 14.68 | F8: -0.06 | G8: -0.23 | H8: 0.99 | I8: 0.5982 | J8: Yes
A10: The variables ROA, Net_Margin, and EBITDA_Margin fail the normality test (p < 0.05), meaning their distributions deviate significantly from normality. This is consistent with what is commonly observed in SME financial data, where profitability metrics tend to be skewed because of loss-making firms or outlier performers. By contrast, Delta_FRI and FRI_score both pass the Shapiro–Wilk test (p > 0.05) and therefore follow a normal distribution. Consequently, non-parametric methods were retained for the subsequent analyses.

Sheet Spearman
A1: Spearman rank correlation | J1: Spearman Correlation Matrix between ΔFRI and Profitability Indicators
A2: Fisher-z 95% CI
A3: Variable Pair | B3: n | C3: rho | D3: p_value | E3: sig | F3: CI_low | G3: CI_high
A4: Delta_FRI vs ROA | B4: 59 | C4: 0.39 | D4: 0.0002 | E4: ** | F4: 0.14 | G4: 0.58
A5: Delta_FRI vs Net_Margin | B5: 59 | C5: 0.39 | D5: 0.0001 | E5: ** | F5: 0.15 | G5: 0.59
A6: Delta_FRI vs EBITDA_Margin | B6: 59 | C6: 0.44 | D6: 0 | E6: *** | F6: 0.21 | G6: 0.62
A8: All three correlations are positive and highly significant (p < 0.001), with Spearman's ρ ranging from 0.39 to 0.44. This indicates that firms experiencing greater improvements in their Financial Resilience Index (ΔFRI) tend to exhibit stronger profitability performance across all three measures (ROA, Net Margin, and EBITDA Margin). The confidence intervals remain entirely above zero, reinforcing the robustness and reliability of these positive associations. While the correlations are moderate in magnitude, they provide initial empirical support for the relevance of improvements in financial resilience as a factor associated with enhanced firm profitability.
M13: Source: Author’s analysis using Python

Sheet Bootstrap
A1: Bootstrap robustness check | J1: Bootstrap Validation of Spearman Correlations
A2: 5,000 resamples of the Spearman ρ — 95% percentile CIs
A3: pair | B3: rho_mean | C3: CI_low | D3: CI_high | E3: excl_zero
A4: Delta_FRI vs ROA | B4: 0.38 | C4: 0.12 | D4: 0.6 | E4: Yes
A5: Delta_FRI vs Net_Margin | B5: 0.39 | C5: 0.14 | D5: 0.6 | E5: Yes
A6: Delta_FRI vs EBITDA_Margin | B6: 0.43 | C6: 0.17 | D6: 0.67 | E6: Yes
A8: The bootstrap test confirms that the Spearman correlations are stable and reliable. After 5,000 random resamples, the results barely change and all confidence intervals remain entirely above zero , meaning the relationships between Delta_FRI and the three profitability variables are robust, not driven by a few unusual observations.
M14: Source: Author’s analysis using Python
H16: The bootstrap distributions appear approximately bell-shaped and centered around the original Spearman coefficients, indicating stable and robust correlation estimates across resamples.

Sheet Wilcoxon
A1: Wilcoxon Signed-Rank Test: FRI Before vs After MPM
A3: Metric | B3: Value | E3: The Wilcoxon Signed-Rank test compares FRI scores before and after MPM's investment. Out of the 15 firms, 10 experienced an improvement in their FRI score, while 5 showed a decline. The average change was positive (+2.21 points) and the median change was +2.39 points, suggesting a general tendency toward improved financial resilience following MPM's involvement. However, the observed increase is not statistically significant (p = 0.359), meaning that the improvement cannot be distinguished from random variation at conventional significance levels. Given the limited sample size and the relatively short observation period, the evidence is insufficient to conclude that MPM's investment systematically improves financial resilience. These findings should therefore be interpreted as indicative rather than conclusive.
A4: N effective | B4: 15
A5: Improved | B5: 10
A6: Declined | B6: 5
A7: Mean difference | B7: 2.21
A8: Median difference | B8: 2.39
A9: W statistic | B9: 43
A10: p-value (two-sided) | B10: 0.3591
A11: p-value (one-sided 'greater') | B11: 0.1796
A12: Effect size r | B12: 0.24
A15: Firm-Level FRI Changes
A17: Firm_ID | B17: FRI_pre | C17: FRI_post | D17: Difference
A18: F01 | B18: 67.15 | C18: 85.61 | D18: 18.46
A19: F02 | B19: 57.78 | C19: 71.76 | D19: 13.98
A20: F03 | B20: 41.68 | C20: 44.08 | D20: 2.39
A21: F04 | B21: 58.3 | C21: 52.32 | D21: -5.97
A22: F05 | B22: 64.21 | C22: 64.01 | D22: -0.2
A23: F06 | B23: 75.3 | C23: 57.14 | D23: -18.16
A24: F07 | B24: 61.1 | C24: 62.54 | D24: 1.43
A25: F08 | B25: 39.29 | C25: 57.88 | D25: 18.58
A26: F09 | B26: 68.96 | C26: 77.21 | D26: 8.25
A27: F10 | B27: 52.09 | C27: 53.31 | D27: 1.22
A28: F11 | B28: 41.97 | C28: 30.29 | D28: -11.68
A29: F12 | B29: 71.88 | C29: 46.06 | D29: -25.82
... A32: F15 | B32: 55.51 | C32: 57.9 | D32: 2.39

Sheet Governance_Score
B1: Governance Score calculation
B3: Method : Score dimension = (sum of 4 questions / 12) × 100 | Final score = average of 4 dimensions
B5: Code | C5: Question | D5: F01 | E5: F02 | F5: F03 | G5: F04 | H5: F05 | I5: F06 | J5: F07 | K5: F08 | L5: F09 | M5: F10 | N5: F11 | O5: F12 | P5: F13 | Q5: F14 | R5: F15
D6: Score | E6: Score | F6: Score | G6: Score | H6: Score | I6: Score | J6: Score | K6: Score | L6: Score | M6: Score | N6: Score | O6: Score | P6: Score | Q6: Score | R6: Score
B7: Dimension 1 : Governance Structure and Strategic Oversight
B8: 1.1 | C8: Does the company rely on a defined body or mechanism (board, management committee or equivalent ... ) that meets on a regular basis ? 0= No identifiable body, decisions are mainly made by one person 1= Informal groups , but with no fixed meetings 2= Defined body , that meets occasionally , not in a regular manner 3= Defined body with scheduled and documented assembly | D8: 3 | E8: 3 | F8: 2 | G8: 3 | H8: 1 | I8: 2 | J8: 3 | K8: 3 | L8: 3 | M8: 3 | N8: 2 | O8: 3 | P8: 3 | Q8: 3 | R8: 3
B9: 1.2 | C9: How many specialized governance committees or equivalent mechanisms does the company have? 0=No specialized committee or equivalent mechanism 1=Informal mechanism only, without a formal committee 2=One specialized committee or equivalent mechanism 3=Two or more specialized committees or equivalent mechanisms | D9: 2 | E9: 3 | F9: 2 | G9: 2 | H9: 2 | I9: 2 | J9: 2 | K9: 2 | L9: 2 | M9: 3 | N9: 2 | O9: 2 | P9: 2 | Q9: 2 | R9: 3
B10: 1.3 | C10: Are the roles and responsibilities of shareholders, managers, and key decision-makers clearly defined and applied ? (e.g : job descriptions, organizational chart,statutes ) ? 0= Not identified 1= Partially identified , but not documented 2= Identified and documented, but not consistently applied in practice 3= Clearly identified, documented, and consistently applied in practice | D10: 3 | E10: 0 | F10: 0 | G10: 0 | H10: 2 | I10: 2 | J10: 1 | K10: 1 | L10: 2 | M10: 1 | N10: 2 | O10: 2 | P10: 1 | Q10: 1 | R10: 2
B11: 1.4 | C11: Are major strategic decisions reviewed using available financial, operational, or risk-related information? 0= No prior analysis is carried out 1= Prior analysis is sometimes considered but it is informal and undocumented. 2= Prior analysis is generally conducted but lacks consistency and formal documentation. 3= Prior analysis is conducted and documented prior to key strategic decisions in an organized way. | D11: 1 | E11: 2 | F11: 1 | G11: 1 | H11: 2 | I11: 2 | J11: 1 | K11: 1 | L11: 2 | M11: 1 | N11: 1 | O11: 1 | P11: 1 | Q11: 2 | R11: 2
B12: Dimension 2 : Financial Reporting, Internal Control and Risk Monitoring
B13: 2.1 | C13: Does the company prepare regular financial reports that support managerial decision-making and governance oversight (balance sheet, income statement...)? 0= No regular financial information is generated for managerial or governance purposes 1= Financial information is prepared irregularly and not well organized to provide the basis for decisions. 2= Financial information is prepared regularly, but its use for decisions or oversight is restricted. 3= Financial information is prepared regularly and used in a structured way for decisions and oversight. | D13: 2 | E13: 3 | F13: 1 | G13: 1 | H13: 2 | I13: 2 | J13: 3 | K13: 2 | L13: 2 | M13: 1 | N13: 2 | O13: 2 | P13: 2 | Q13: 1 | R13: 1
B14: 2.2 | C14: Are documented internal control procedures set up for key financial and operational processes (Authorization limits, segregation of duties, access controls..) ? 0= No identifiable internal control procedures exist. 1= Internal controls exist but are not formalized or documented. 2= Internal control procedures are documented but not consistently implemented. 3= Internal control procedures are documented and consistently implemented. | D14: 3 | E14: 2 | F14: 3 | G14: 3 | H14: 1 | I14: 3 | J14: 3 | K14: 2 | L14: 3 | M14: 1 | N14: 2 | O14: 3 | P14: 3 | Q14: 3 | R14: 2
B15: 2.3 | C15: Does the company identify and monitor its main business, financial, and operational risks ? 0= There is no established process to identify or monitor the company’s principal risks. 1= Some risks are recognized, but in a limited or unstructured manner. 2= The company identifies and monitors its principal risks, but in a limited, unstructured or poorly documented manner. 3= The company identifies and monitors its principal risks through a structured, documented and regularly applied process. | D15: 3 | E15: 3 | F15: 1 | G15: 3 | H15: 2 | I15: 1 | J15: 2 | K15: 3 | L15: 2 | M15: 2 | N15: 3 | O15: 2 | P15: 2 | Q15: 2 | R15: 3
B16: 2.4 | C16: Is the company’s financial information or reporting process reviewed by an external or independent party ? 0= No independent or external review exists. 1= Independent or external review occurs only on an exceptional or ad hoc basis. 2= Some independent or external review exists, but the scope is limited, irregular or only applies in part to the organization’s information or controls. 3= The organization’s financial information, internal controls or reporting process is subject to regular and identifiable independent or external review. | D16: 3 | E16: 2 | F16: 3 | G16: 2 | H16: 3 | I16: 3 | J16: 3 | K16: 3 | L16: 3 | M16: 3 | N16: 2 | O16: 3 | P16: 2 | Q16: 2 | R16: 3
B17: Dimension 3 : Shareholder and Investor Rights and Transparency
B18: 3.1 | C18: Do owners/shareholders have well defined rights to approve major changes in the ownership or control of the company? 0= No clearly defined approval rights exist for major changes in ownership or control. 1= Some approval rights exist, but they are informal, incomplete or not documented. 2= Approval rights are defined and documented, but they are not necessarily complete, up to date or consistently applied. 3= Approval rights are clearly defined, documented and consistently applied for major changes in ownership or control. | D18: 3 | E18: 3 | F18: 2 | G18: 2 | H18: 0 | I18: 2 | J18: 3 | K18: 2 | L18: 3 | M18: 3 | N18: 2 | O18: 3 | P18: 3 | Q18: 3 | R18: 2
B19: 3.2 | C19: Does the company have a structured process for communicating major decisions and significant developments to owners/shareholders and investors ? 0= No structured communication process exists for informing shareholders or investors of major decisions and significant developments. 1= Some information is shared, but communication is informal, occasional or incomplete. 2= A communication process exists, but it is only partly structured, irregular or not consistently documented. 3= A structured and identifiable communication process exists for regularly informing shareholders or investors of major decisions and significant developments. | D19: 3 | E19: 3 | F19: 1 | G19: 3 | H19: 1 | I19: 0 | J19: 2 | K19: 3 | L19: 3 | M19: 2 | N19: 3 | O19: 2 | P19: 2 | Q19: 2 | R19: 3
B20: 3.3 | C20: Does the company have clear rules or practices to identify and manage conflicts of interest (e.g., between owners/shareholders, managers, family members or related parties)? 0= No identifiable rules or practices exist to manage conflicts of interest. 1= Awareness of conflicts of interest exists, but no formal or consistent rules exist. 2= Some rules or practices exist, although they may be informal, partial or inconsistent. 3= Clear and identifiable rules or practices exist to identify and manage conflicts of interest. | D20: 3 | E20: 3 | F20: 2 | G20: 3 | H20: 0 | I20: 1 | J20: 3 | K20: 2 | L20: 3 | M20: 2 | N20: 2 | O20: 3 | P20: 3 | Q20: 3 | R20: 0
B21: 3.4 | C21: Are there clear rules governing the entry of new owners and the transfer or exit of existing ownership interests? 0= No clear rules are available for the entry of new owners and the transfer or exit of ownership interests. 1= Rules are available but informal and incomplete. 2= Clear rules are available but not always complete, up to date or consistently applied. 3= Clear rules are defined and consistently applied for the entry of new owners and the transfer or exit of ownership interests. | D21: 3 | E21: 2 | F21: 1 | G21: 0 | H21: 2 | I21: 2 | J21: 2 | K21: 2 | L21: 0 | M21: 3 | N21: 1 | O21: 0 | P21: 0 | Q21: 1 | R21: 2
B22: Dimension 4 : Ethics, Compliance and Business Continuity
B23: 4.1 | C23: Does your company have a succession plan or continuity procedure for key roles (e.g., CEO, founder, key manager)? 0= No succession plan or continuity procedure exists for key managerial roles. 1= Succession or continuity is informally discussed but it is not documented. 2= Partial succession plan or continuity procedure exists for some key roles. 3= Formal succession plan or continuity procedure exists for key managerial roles and it is clearly documented. | D23: 3 | E23: 0 | F23: 0 | G23: 1 | H23: 0 | I23: 1 | J23: 1 | K23: 2 | L23: 2 | M23: 0 | N23: 0 | O23: 0 | P23: 1 | Q23: 0 | R23: 1
B24: 4.2 | C24: Are there written or clearly communicated rules regarding ethics, confidentiality and professional conduct? 0= No written or clearly communicated rules exist. 1= Some informal or partially communicated rules exist, but they are limited and inconsistent. 2= Rules are defined in writing or clearly communicated, but their application is uneven in practice. 3= Rules are clearly defined, communicated and consistently applied in practice. | D24: 3 | E24: 2 | F24: 2 | G24: 2 | H24: 1 | I24: 1 | J24: 3 | K24: 3 | L24: 3 | M24: 1 | N24: 2 | O24: 2 | P24: 2 | Q24: 2 | R24: 2
B25: 4.3 | C25: Are irregularities, breaches, or non-compliance situations identified and followed up where necessary through corrective actions? 0= No identifiable process exists to identify or follow up irregularities or non-compliance situations. 1= Some follow-up exists, but it is informal,or inconsistent. 2= Irregularities or non-compliance situations are generally identified and followed up, but the process is only partly structured or not consistently documented. 3= Irregularities or non-compliance situations are identified and followed up through a clear, structured, and identifiable process. | D25: 2 | E25: 2 | F25: 1 | G25: 2 | H25: 2 | I25: 2 | J25: 2 | K25: 3 | L25: 2 | M25: 1 | N25: 2 | O25: 1 | P25: 2 | Q25: 3 | R25: 2
B26: 4.4 | C26: Does the company have procedures to monitor and respect its main legal, tax, social, and regulatory obligations? 0 = No clear rules or follow-up. 1 = Some checks exist, but informally. 2 = Rules exist, but they are incomplete or not always followed 3 = Clear rules exist and are followed regularly | D26: 2 | E26: 3 | F26: 2 | G26: 1 | H26: 1 | I26: 2 | J26: 2 | K26: 1 | L26: 2 | M26: 1 | N26: 1 | O26: 2 | P26: 1 | Q26: 1 | R26: 1
B29: Results
B30: Dimension 1 - total | D30: =IF(COUNT(D8:D11)=4,SUM(D8:D11),"") -> 9 | E30: =IF(COUNT(E8:E11)=4,SUM(E8:E11),"") -> 8 | F30: =IF(COUNT(F8:F11)=4,SUM(F8:F11),"") -> 5 | G30: =IF(COUNT(G8:G11)=4,SUM(G8:G11),"") -> 6 | H30: =IF(COUNT(H8:H11)=4,SUM(H8:H11),"") -> 7 | I30: =IF(COUNT(I8:I11)=4,SUM(I8:I11),"") -> 8 | J30: =IF(COUNT(J8:J11)=4,SUM(J8:J11),"") -> 7 | K30: =IF(COUNT(K8:K11)=4,SUM(K8:K11),"") -> 7 | ... R30: =IF(COUNT(R8:R11)=4,SUM(R8:R11),"") -> 10
B31: Dimension 1 - score | D31: =IF(D30="","",(D30/12)*100) -> 75 | E31: =IF(E30="","",(E30/12)*100) -> 66.666667 | F31: =IF(F30="","",(F30/12)*100) -> 41.666667 | G31: =IF(G30="","",(G30/12)*100) -> 50 | H31: =IF(H30="","",(H30/12)*100) -> 58.333333 | I31: =IF(I30="","",(I30/12)*100) -> 66.666667 | J31: =IF(J30="","",(J30/12)*100) -> 58.333333 | K31: =IF(K30="","",(K30/12)*100) -> 58.333333 | ... R31: =IF(R30="","",(R30/12)*100) -> 83.333333
B32: Dimension 2 - total | D32: =IF(COUNT(D13:D16)=4,SUM(D13:D16),"") -> 11 | E32: =IF(COUNT(E13:E16)=4,SUM(E13:E16),"") -> 10 | F32: =IF(COUNT(F13:F16)=4,SUM(F13:F16),"") -> 8 | G32: =IF(COUNT(G13:G16)=4,SUM(G13:G16),"") -> 9 | H32: =IF(COUNT(H13:H16)=4,SUM(H13:H16),"") -> 8 | I32: =IF(COUNT(I13:I16)=4,SUM(I13:I16),"") -> 9 | J32: =IF(COUNT(J13:J16)=4,SUM(J13:J16),"") -> 11 | K32: =IF(COUNT(K13:K16)=4,SUM(K13:K16),"") -> 10 | ... R32: =IF(COUNT(R13:R16)=4,SUM(R13:R16),"") -> 9
B33: Dimension 2 - score | D33: =IF(D32="","",(D32/12)*100) -> 91.666667 | E33: =IF(E32="","",(E32/12)*100) -> 83.333333 | F33: =IF(F32="","",(F32/12)*100) -> 66.666667 | G33: =IF(G32="","",(G32/12)*100) -> 75 | H33: =IF(H32="","",(H32/12)*100) -> 66.666667 | I33: =IF(I32="","",(I32/12)*100) -> 75 | J33: =IF(J32="","",(J32/12)*100) -> 91.666667 | K33: =IF(K32="","",(K32/12)*100) -> 83.333333 | ... R33: =IF(R32="","",(R32/12)*100) -> 75
B34: Dimension 3 - total | D34: =IF(COUNT(D18:D21)=4,SUM(D18:D21),"") -> 12 | E34: =IF(COUNT(E18:E21)=4,SUM(E18:E21),"") -> 11 | F34: =IF(COUNT(F18:F21)=4,SUM(F18:F21),"") -> 6 | G34: =IF(COUNT(G18:G21)=4,SUM(G18:G21),"") -> 8 | H34: =IF(COUNT(H18:H21)=4,SUM(H18:H21),"") -> 3 | I34: =IF(COUNT(I18:I21)=4,SUM(I18:I21),"") -> 5 | J34: =IF(COUNT(J18:J21)=4,SUM(J18:J21),"") -> 10 | K34: =IF(COUNT(K18:K21)=4,SUM(K18:K21),"") -> 9 | ... R34: =IF(COUNT(R18:R21)=4,SUM(R18:R21),"") -> 7
B35: Dimension 3 - score | D35: =IF(D34="","",(D34/12)*100) -> 100 | E35: =IF(E34="","",(E34/12)*100) -> 91.666667 | F35: =IF(F34="","",(F34/12)*100) -> 50 | G35: =IF(G34="","",(G34/12)*100) -> 66.666667 | H35: =IF(H34="","",(H34/12)*100) -> 25 | I35: =IF(I34="","",(I34/12)*100) -> 41.666667 | J35: =IF(J34="","",(J34/12)*100) -> 83.333333 | K35: =IF(K34="","",(K34/12)*100) -> 75 | ... R35: =IF(R34="","",(R34/12)*100) -> 58.333333
B36: Dimension 4 - total | D36: =IF(COUNT(D23:D26)=4,SUM(D23:D26),"") -> 10 | E36: =IF(COUNT(E23:E26)=4,SUM(E23:E26),"") -> 7 | F36: =IF(COUNT(F23:F26)=4,SUM(F23:F26),"") -> 5 | G36: =IF(COUNT(G23:G26)=4,SUM(G23:G26),"") -> 6 | H36: =IF(COUNT(H23:H26)=4,SUM(H23:H26),"") -> 4 | I36: =IF(COUNT(I23:I26)=4,SUM(I23:I26),"") -> 6 | J36: =IF(COUNT(J23:J26)=4,SUM(J23:J26),"") -> 8 | K36: =IF(COUNT(K23:K26)=4,SUM(K23:K26),"") -> 9 | ... R36: =IF(COUNT(R23:R26)=4,SUM(R23:R26),"") -> 6
B37: Dimension 4 - score | D37: =IF(D36="","",(D36/12)*100) -> 83.333333 | E37: =IF(E36="","",(E36/12)*100) -> 58.333333 | F37: =IF(F36="","",(F36/12)*100) -> 41.666667 | G37: =IF(G36="","",(G36/12)*100) -> 50 | H37: =IF(H36="","",(H36/12)*100) -> 33.333333 | I37: =IF(I36="","",(I36/12)*100) -> 50 | J37: =IF(J36="","",(J36/12)*100) -> 66.666667 | K37: =IF(K36="","",(K36/12)*100) -> 75 | ... R37: =IF(R36="","",(R36/12)*100) -> 50
B38: Final Score | D38: =IF(COUNT(D31,D33,D35,D37)=4,AVERAGE(D31,D33,D35,D37),"") -> 87.5 | E38: =IF(COUNT(E31,E33,E35,E37)=4,AVERAGE(E31,E33,E35,E37),"") -> 75 | F38: =IF(COUNT(F31,F33,F35,F37)=4,AVERAGE(F31,F33,F35,F37),"") -> 50 | G38: =IF(COUNT(G31,G33,G35,G37)=4,AVERAGE(G31,G33,G35,G37),"") -> 60.416667 | H38: =IF(COUNT(H31,H33,H35,H37)=4,AVERAGE(H31,H33,H35,H37),"") -> 45.833333 | I38: =IF(COUNT(I31,I33,I35,I37)=4,AVERAGE(I31,I33,I35,I37),"") -> 58.333333 | J38: =IF(COUNT(J31,J33,J35,J37)=4,AVERAGE(J31,J33,J35,J37),"") -> 75 | K38: =IF(COUNT(K31,K33,K35,K37)=4,AVERAGE(K31,K33,K35,K37),"") -> 72.916667 | ... R38: =IF(COUNT(R31,R33,R35,R37)=4,AVERAGE(R31,R33,R35,R37),"") -> 66.666667
D41: F01 | E41: F02 | F41: F03 | G41: F04 | H41: F05 | I41: F06 | J41: F07 | K41: F08 | L41: F09 | M41: F10 | N41: F11 | O41: F12 | P41: F13 | Q41: F14 | R41: F15
D42: 87.5 | E42: 75 | F42: 50 | G42: 60.416667 | H42: 45.833333 | I42: 58.333333 | J42: 75 | K42: 72.916667 | L42: 77.083333 | M42: 58.333333 | N42: 60.416667 | O42: 64.583333 | P42: 62.5 | Q42: 64.583333 | R42: 66.666667
M61: Source : Author

Sheet G_score vs FRI
A1: Cross-instrument validation: G_score vs FRI
J2: Relationship between G_score and FRI
A3: pair | B3: n | C3: rho | D3: p_value | E3: sig | F3: CI_low | G3: CI_high
A4: G score vs FRI_score | B4: 15 | C4: 0.67 | D4: 0.0068 | E4: ** | F4: 0.23 | G4: 0.88
A7: The correlation between G score and FRI_score is positive and statistically significant (ρ = 0.67, p = 0.01), indicating that firms with stronger governance practices tend to exhibit higher levels of financial resilience. The confidence interval [0.23, 0.88] remains entirely above zero, supporting the robustness of this positive association. Although the sample includes only 15 firms, the relatively strong correlation provides initial evidence that governance quality may be an important factor associated with financial resilience.
L20: Source: Author’s analysis using Python

Sheet Synthesis
A1: Synthesis
A3: Hypothesis | B3: Test | C3: Statistic | D3: p-value | E3: Result
A4: H1 Delta_FRI is positively associated with profitability | B4: Spearman | C4: ρ = 0.39-0.44 | D4: all p < 0.001 | E4: Supported
A5: Robustness validation of H1 | B5: Bootstrap 5,000 | C5: 95% CIs exclude 0 | D5: - | E5: Robust
A6: H2 FRI improves post-MPM | B6: Wilcoxon (one-sided) | C6: W = 43.00 | D6: 0.3591 | E6: Not supported
A7: H3 G score is positively associated with FRI | B7: Spearman | C7: ρ = 0.67 | D7: 0.01 | E7: Supported
A11: Overall, the results provide substantial support for the proposed framework. Improvements in financial resilience are positively associated with profitability (H1), and bootstrap validation confirms the robustness of this relationship. In contrast, the Wilcoxon test does not provide sufficient statistical evidence that financial resilience systematically improves following MPM's investment (H2), despite the predominance of positive firm-level changes. Finally, governance quality is positively associated with financial resilience (H3), suggesting that better-governed firms tend to exhibit stronger resilience profiles. Overall, two of the three hypotheses are supported, while the evidence regarding post-investment improvements in financial resilience remains inconclusive.

Sheet Cluster_firms
A1: Firm-Level Financial Resilience Clusters
A2: K-means classification based on standardized pillar scores (k = 3)
A3: Firm_ID | B3: P1 Liquidity | C3: P2 Cash Generation | D3: P3 Capital structure | E3: P4 Debt Sustainability | F3: Cluster | G3: Final-Year FRI
A4: F03 | B4: 29.62 | C4: 58.49 | D4: 23.05 | E4: 74.09 | F4: Fragile | G4: 46.31
A5: F12 | B5: 38.64 | C5: 13.2 | D5: 64.99 | E5: 43.48 | F5: Fragile | G5: 40.08
A6: F11 | B6: 24.73 | C6: 0 | D6: 44.95 | E6: 2.79 | F6: Fragile | G6: 18.12
A7: F14 | B7: 77.22 | C7: 22.74 | D7: 93.67 | E7: 56.1 | F7: Intermediate | G7: 62.43
A8: F06 | B8: 83.64 | C8: 9.62 | D8: 98.19 | E8: 0 | F8: Intermediate | G8: 47.86
A9: F01 | B9: 62.87 | C9: 93.46 | D9: 91.95 | E9: 100 | F9: Resilient | G9: 87.07
A10: F02 | B10: 53.62 | C10: 99.46 | D10: 74.4 | E10: 86.23 | F10: Resilient | G10: 78.43
A11: F09 | B11: 75.85 | C11: 71.41 | D11: 89.73 | E11: 72.93 | F11: Resilient | G11: 77.48
A12: F07 | B12: 51.31 | C12: 68.86 | D12: 68.87 | E12: 78.98 | F12: Resilient | G12: 67
A13: F05 | B13: 49.38 | C13: 68.48 | D13: 67.55 | E13: 74.87 | F13: Resilient | G13: 65.07
A14: F13 | B14: 51.15 | C14: 56.08 | D14: 88.62 | E14: 59.79 | F14: Resilient | G14: 63.91
A15: F08 | B15: 57.42 | C15: 82.65 | D15: 66.73 | E15: 47.81 | F15: Resilient | G15: 63.65
... A18: F10 | B18: 62.09 | C18: 46.09 | D18: 67.94 | E18: 58.6 | F18: Resilient | G18: 58.68
A20: Note: F06 and F11 contain at least one zero-valued standardized pillar score due to extreme observations after rescaling; these observations were retained in the clustering analysis.

Sheet Cluster_summary
A1: Mean Financial Pillar Scores by Cluster | M1: Chart : Portfolio Mapping of Firms on the First Two Principal Components
A3: Cluster | B3: Number of firms | C3: P1 Liquidity | D3: P2 Cash Generation | E3: P3 Capital structure | F3: P4 Debt Sustainability | G3: Mean FRI
A4: Fragile | B4: 3 | C4: 31 | D4: 23.9 | E4: 44.33 | F4: 40.12 | G4: 34.84
A5: Intermediate | B5: 2 | C5: 80.43 | D5: 16.18 | E5: 95.93 | F5: 28.05 | G5: 55.14
A6: Resilient | B6: 10 | C6: 58.91 | D6: 68.01 | E6: 76.12 | F6: 69.1 | G6: 68.04
A8: The Resilient cluster shows the strongest overall financial profile, particularly in cash generation and debt sustainability, resulting in the highest mean FRI. In contrast, Fragile firms display weaker performance across most financial dimensions, leading to the lowest mean FRI. Although the Intermediate cluster records the highest liquidity and capital structure scores, weaker cash generation and debt sustainability reduce its overall resilience. These findings suggest that financial resilience is driven by balanced performance across multiple pillars rather than excellence in a single dimension.
A10: Sector Distribution Across Clusters
A12: Cluster | B12: Agri-food Industry | C12: Manufacturing Industry | D12: Services & Commerce
A13: Fragile | B13: =(1/B4) -> 0.33333333 | C13: =2/B4 -> 0.66666667 | D13: =0/B4 -> 0
A14: Intermediate | B14: =0/B5 -> 0 | C14: =2/2 -> 1 | D14: =0/B5 -> 0
A15: Resilient | B15: =3/B6 -> 0.3 | C15: =4/B6 -> 0.4 | D15: =3/B6 -> 0.3
Q16: Source: Author’s analysis using Python
A17: The sector distribution across clusters reveals noticeable differences in the positioning of SMEs within the resilience profiles. Fragile firms are predominantly concentrated in the manufacturing industry (67%), while the resilient cluster displays a more diversified composition across agri-food, manufacturing, and services activities. The intermediate cluster is composed exclusively of manufacturing firms. These observations suggest that resilience profiles are influenced by sectoral characteristics, although the limited sample size means that the findings should be interpreted as indicative rather than conclusive sectoral trends. | L17: The PCA projection reveals a relatively clear separation between the three resilience profiles identified through the clustering analysis. Fragile firms are mainly positioned on the left and lower areas of the map, while resilient firms appear more concentrated in the central and right-hand regions. Overall, the figure visually supports the relevance of the three-cluster classification retained for the portfolio segmentation, despite a limited overlap between certain firms.

Sheet Silhouette
A1: Cluster Validation Indicators
A3: k | B3: silhouette | C3: inertia
A4: 2 | B4: 0.39 | C4: 37.65
A5: 3 | B5: 0.36 | C5: 23.73
A6: 4 | B6: 0.36 | C6: 17.3
A8: The silhouette score is slightly higher for k=2 (0.39) than for k=3 (0.36). However, the three-cluster solution was retained for the analysis because the difference in silhouette values is minimal, while k=3 provides greater interpretability by distinguishing between Resilient, Intermediate, and Fragile firms. The three-cluster specification also aligns more closely with the patterns observed in the PCA projection and offers a more informative representation of the portfolio's heterogeneity. Consequently, the three-cluster solution was adopted for the subsequent analysis.

Sheet Benchmarking
A1: Within-Sector FRI Benchmarking | K1: Chart : Within-Sector Relative FRI Gaps
A3: Firm_ID | B3: Sector | C3: Last_FRI | D3: Sector_median | E3: FRI_relative | F3: position
A4: F02 | B4: Agri-food Industry | C4: 78.43 | D4: 64.36 | E4: 14.07 | F4: Leader
A5: F05 | B5: Agri-food Industry | C5: 65.07 | D5: 64.36 | E5: 0.71 | F5: Leader
A6: F08 | B6: Agri-food Industry | C6: 63.65 | D6: 64.36 | E6: -0.71 | F6: Follower
A7: F12 | B7: Agri-food Industry | C7: 40.08 | D7: 64.36 | E7: -24.28 | F7: Follower
A8: F09 | B8: Manufacturing Industry | C8: 77.48 | D8: 58.81 | E8: 18.67 | F8: Leader
A9: F14 | B9: Manufacturing Industry | C9: 62.43 | D9: 58.81 | E9: 3.62 | F9: Leader
A10: F15 | B10: Manufacturing Industry | C10: 60.14 | D10: 58.81 | E10: 1.33 | F10: Leader
A11: F04 | B11: Manufacturing Industry | C11: 58.94 | D11: 58.81 | E11: 0.13 | F11: Leader
A12: F10 | B12: Manufacturing Industry | C12: 58.68 | D12: 58.81 | E12: -0.13 | F12: Follower
A13: F06 | B13: Manufacturing Industry | C13: 47.86 | D13: 58.81 | E13: -10.95 | F13: Follower
A14: F03 | B14: Manufacturing Industry | C14: 46.31 | D14: 58.81 | E14: -12.5 | F14: Follower
A15: F11 | B15: Manufacturing Industry | C15: 18.12 | D15: 58.81 | E15: -40.69 | F15: Follower
... A18: F13 | B18: Services and Commerce | C18: 63.91 | D18: 67 | E18: -3.09 | F18: Follower
Q19: Source: Author’s analysis using Python
A20: The within-sector benchmarking results show a relatively balanced distribution, with 8 firms classified as Leaders and 7 as Followers. Each firm is compared with the median FRI of its own sector in order to evaluate its relative resilience position among direct peers. The median was preferred over the mean to reduce the influence of extreme values in the small sample. The results reveal substantial differences in relative resilience within sectors. For example, firms such as F01 and F02 display strong positive gaps, indicating resilience levels well above their sector medians, whereas firms such as F11 and F12 exhibit large negative gaps, reflecting weaker relative resilience. Overall, positive FRI gaps indicate stronger resilience performance relative to sector peers, while negative gaps suggest below-median resilience levels. | J20: The figure highlights differences in firms' relative resilience positions within each sector. Manufacturing firms display the widest dispersion, with both strong positive and negative deviations from the sector median, indicating heterogeneous resilience profiles. In contrast, Agri-food and Services & Commerce firms exhibit more concentrated distributions around their respective sector benchmarks, although a few firms show substantial positive or negative gaps. The visualization also helps identify firms that significantly outperform or underperform their direct sector peers, providing additional insight into the relative positioning of SMEs within each sector.

Sheet Decision table
A1: Decision Scores and Recommendations
A3: Firm | B3: Sector | C3: FRI | D3: Governance Score | E3: Decision Score | F3: Recommendation
A4: F01 | B4: Services and Commerce | C4: 87.07 | D4: 87.5 | E4: 87.2 | F4: Reinforce
A5: F02 | B5: Agri-food Industry | C5: 78.43 | D5: 75 | E5: 77.4 | F5: Reinforce
A6: F09 | B6: Manufacturing Industry | C6: 77.48 | D6: 77.08 | E6: 77.36 | F6: Reinforce
A7: F07 | B7: Services and Commerce | C7: 67 | D7: 75 | E7: 69.4 | F7: Reinforce
A8: F08 | B8: Agri-food Industry | C8: 63.65 | D8: 72.92 | E8: 66.43 | F8: Reinforce
A9: F13 | B9: Services and Commerce | C9: 63.91 | D9: 62.5 | E9: 63.49 | F9: Reinforce
A10: F14 | B10: Manufacturing Industry | C10: 62.43 | D10: 64.58 | E10: 63.08 | F10: Maintain
A11: F15 | B11: Manufacturing Industry | C11: 60.14 | D11: 66.67 | E11: 62.1 | F11: Maintain
A12: F04 | B12: Manufacturing Industry | C12: 58.94 | D12: 60.42 | E12: 59.38 | F12: Maintain
A13: F05 | B13: Agri-food Industry | C13: 65.07 | D13: 45.8 | E13: 59.29 | F13: Maintain
A14: F10 | B14: Manufacturing Industry | C14: 58.68 | D14: 58.33 | E14: 58.58 | F14: Maintain
A15: F06 | B15: Manufacturing Industry | C15: 47.86 | D15: 58.3 | E15: 50.99 | F15: Watchlist
... A18: F11 | B18: Manufacturing Industry | C18: 18.12 | D18: 60.4 | E18: 30.8 | F18: Watchlist
A20: Note: Thresholds (58.58 and 63.49) correspond to the 33rd and 67th percentiles of the Decision Score distribution, dividing the sample into three tertiles: bottom tertile (Watchlist), middle tertile (Maintain), and top tertile (Reinforce).
A22: The decision framework differentiates firms according to their combined financial resilience and governance profiles. Firms classified as "Reinforce" exhibit the strongest overall positioning, characterized by high Decision Scores and consistently strong performance across both dimensions. In contrast, firms placed in the "Watchlist" category generally display lower composite scores, indicating greater vulnerability and the need for closer monitoring. The "Maintain" category represents intermediate profiles with relatively balanced but non-leading performance levels. Overall, the classification provides a structured segmentation of firms according to their combined resilience and governance characteristics, supporting portfolio monitoring and decision-making.

Sheet SensitivityAnalysis
A1: Sensitivity Analysis of Weighting Schemes
A3: Firm | B3: Decision Score (70/30) | C3: Recommendation (70/30) | D3: Decision Score (60/40) | E3: Recommendation (60/40) | F3: Decision Score (50/50) | G3: Recommendation ( 50/50)
A4: F01 | B4: 87.2 | C4: Reinforce | D4: 87.24 | E4: Reinforce | F4: 87.28 | G4: Reinforce
A5: F02 | B5: 77.4 | C5: Reinforce | D5: 77.06 | E5: Reinforce | F5: 76.72 | G5: Reinforce
A6: F09 | B6: 77.36 | C6: Reinforce | D6: 77.32 | E6: Reinforce | F6: 77.28 | G6: Reinforce
A7: F07 | B7: 69.4 | C7: Reinforce | D7: 70.2 | E7: Reinforce | F7: 71 | G7: Reinforce
A8: F08 | B8: 66.43 | C8: Reinforce | D8: 67.36 | E8: Reinforce | F8: 68.28 | G8: Reinforce
A9: F13 | B9: 63.49 | C9: Reinforce | D9: 63.35 | E9: Maintain | F9: 63.2 | G9: Maintain
A10: F14 | B10: 63.08 | C10: Maintain | D10: 63.29 | E10: Maintain | F10: 63.51 | G10: Reinforce
A11: F15 | B11: 62.1 | C11: Maintain | D11: 62.75 | E11: Maintain | F11: 63.4 | G11: Maintain
A12: F04 | B12: 59.38 | C12: Maintain | D12: 59.53 | E12: Maintain | F12: 59.68 | G12: Maintain
A13: F05 | B13: 59.29 | C13: Maintain | D13: 57.36 | E13: Watchlist | F13: 55.43 | G13: Watchlist
A14: F10 | B14: 58.58 | C14: Maintain | D14: 58.54 | E14: Watchlist | F14: 58.51 | G14: Watchlist
A15: F06 | B15: 50.99 | C15: Watchlist | D15: 52.04 | E15: Watchlist | F15: 53.08 | G15: Watchlist
... A18: F11 | B18: 30.8 | C18: Watchlist | D18: 35.03 | E18: Watchlist | F18: 39.26 | G18: Watchlist
A20: The sensitivity analysis indicates that the decision framework remains relatively stable under alternative weighting schemes. Most firms retain the same recommendation category across the three specifications, with only a limited number of firms experiencing classification changes near the decision thresholds. Importantly, the highest-ranked ("Reinforce") and lowest-ranked ("Watchlist") firms remain largely consistent across all scenarios. These results suggest that the framework's main conclusions are not highly sensitive to moderate variations in weighting assumptions, supporting the robustness of the proposed decision framework.

Sheet Case study
A1: Case study — three contrasting firms
A2: Illustrative firms selected from the three recommendation categories.
A4: Firm | B4: Sector | C4: Latest FRI | D4: G_score | E4: Decision Score | F4: Recommendation | G4: Liquidity | H4: Cash Gen. | I4: Capital Str. | J4: Debt Sust.
A5: F01 | B5: Services and Commerce | C5: 87.07 | D5: 87.5 | E5: 87.2 | F5: Reinforce | G5: 62.87 | H5: 93.46 | I5: 91.95 | J5: 100
A6: F04 | B6: Manufacturing Industry | C6: 58.94 | D6: 60.42 | E6: 59.38 | F6: Maintain | G6: 55.56 | H6: 52.91 | I6: 67.82 | J6: 59.45
A7: F11 | B7: Manufacturing Industry | C7: 18.12 | D7: 60.4 | E7: 30.8 | F7: Watchlist | G7: 24.73 | H7: 0 | I7: 44.95 | J7: 2.79
A10: Interpretation of the Three Profiles
A12: F01 | C12: F01 represents the strongest profile within the sample, combining very high financial resilience (FRI = 87.07) with strong governance quality and the highest Decision Score. The firm displays strong performance across all financial pillars, particularly in cash generation and debt sustainability, indicating a robust ability to generate liquidity while preserving financial stability. Operating in the services and commerce sector, the company benefits from a relatively dynamic activity profile with stronger adaptability and lower structural pressure compared to more capital-intensive sectors. The combination of balanced financial fundamentals and governance strength positions the firm as a significant value-supporting component within the portfolio. Its profile suggests a strong capacity to sustain growth initiatives, absorb adverse market conditions, and maintain operational resilience in an environment characterized by economic uncertainty and financing constraints. Such characteristics reinforce the firm’s attractiveness within an investment-oriented perspective by supporting long-term value creation potential alongside comparatively lower financial vulnerability.
A14: F04 | C14: F04 represents an intermediate profile within the portfolio, combining moderate financial resilience with adequate governance quality. The firm displays balanced but non-leading performance across the financial dimensions, with capital structure representing its main strength, while liquidity and cash generation remain at moderate levels. Operating in the plastic packaging industry, F04 was significantly affected by the COVID-19 crisis, which weakened operating performance and created financial imbalances that continue to influence its resilience profile. Since MPM's investment, several governance and operational improvements have been implemented to strengthen financial management, internal controls, and reporting practices. These initiatives have contributed to stabilizing the company and supporting its gradual recovery, although further efforts remain necessary to consolidate financial performance and long-term stability.
A16: F11 | C16: F11 represents the most fragile profile within the sample, recording the lowest Financial Resilience Index (FRI = 18.12) and the weakest Decision Score. Although the governance dimension remains relatively acceptable, the firm exhibits major weaknesses across several financial pillars, particularly cash generation and debt sustainability, indicating significant financial pressure and limited operational flexibility. Operating in the manufacturing sector, and more specifically in fiber cement activities, the company is exposed to structurally demanding industrial conditions characterized by high operating intensity, elevated financing needs, and sensitivity to economic fluctuations. The strong imbalance between governance quality and financial performance suggests that managerial structures alone have not been sufficient to offset the firm’s operational and financial vulnerabilities. This profile therefore calls for closer monitoring and targeted corrective measures aimed at restoring financial stability and improving cash generation capacity. Overall, the “Watchlist” classification reflects a comparatively vulnerable position within the portfolio, with limited resilience under adverse economic conditions and higher exposure to financial risk.

Sheet Decision Framework – Charts
A1: Figures
A3: Decision Score by firm
A23: Portfolio map FRI × G_score
A43: Weight sensitivity
A63: Case study — three contrasting firms
